{"builtWith":"0.15.15","comments":[{"LineComment":" | ColorPicker Component"}],"decls":[{"annotation":{"meta":null,"sourceSpan":{"end":[0,0],"start":[0,0]}},"bindType":"NonRec","expression":{"abstraction":{"annotation":{"meta":{"metaType":"IsForeign"},"sourceSpan":{"end":[109,76],"start":[109,74]}},"type":"Var","value":{"identifier":"append","moduleName":["Data","Semigroup"]}},"annotation":{"meta":{"metaType":"IsSyntheticApp"},"sourceSpan":{"end":[110,98],"start":[109,3]}},"argument":{"annotation":{"meta":null,"sourceSpan":{"end":[0,0],"start":[0,0]}},"type":"Var","value":{"identifier":"semigroupString","moduleName":["Data","Semigroup"]}},"type":"App"},"identifier":"append"},{"annotation":{"meta":null,"sourceSpan":{"end":[0,0],"start":[0,0]}},"bindType":"NonRec","expression":{"abstraction":{"annotation":{"meta":{"metaType":"IsForeign"},"sourceSpan":{"end":[129,21],"start":[129,17]}},"type":"Var","value":{"identifier":"pure","moduleName":["Control","Applicative"]}},"annotation":{"meta":{"metaType":"IsSyntheticApp"},"sourceSpan":{"end":[129,26],"start":[129,17]}},"argument":{"annotation":{"meta":null,"sourceSpan":{"end":[0,0],"start":[0,0]}},"type":"Var","value":{"identifier":"applicativeHalogenM","moduleName":["Halogen","Query","HalogenM"]}},"type":"App"},"identifier":"pure"},{"annotation":{"meta":null,"sourceSpan":{"end":[0,0],"start":[0,0]}},"bindType":"NonRec","expression":{"abstraction":{"annotation":{"meta":{"metaType":"IsForeign"},"sourceSpan":{"end":[130,29],"start":[130,20]}},"type":"Var","value":{"identifier":"modify_","moduleName":["Control","Monad","State","Class"]}},"annotation":{"meta":{"metaType":"IsSyntheticApp"},"sourceSpan":{"end":[130,76],"start":[130,20]}},"argument":{"annotation":{"meta":null,"sourceSpan":{"end":[0,0],"start":[0,0]}},"type":"Var","value":{"identifier":"monadStateHalogenM","moduleName":["Halogen","Query","HalogenM"]}},"type":"App"},"identifier":"modify_"},{"annotation":{"meta":null,"sourceSpan":{"end":[0,0],"start":[0,0]}},"bindType":"NonRec","expression":{"abstraction":{"annotation":{"meta":{"metaType":"IsForeign"},"sourceSpan":{"end":[131,49],"start":[131,46]}},"type":"Var","value":{"identifier":"not","moduleName":["Data","HeytingAlgebra"]}},"annotation":{"meta":{"metaType":"IsSyntheticApp"},"sourceSpan":{"end":[131,58],"start":[131,46]}},"argument":{"annotation":{"meta":null,"sourceSpan":{"end":[0,0],"start":[0,0]}},"type":"Var","value":{"identifier":"heytingAlgebraBoolean","moduleName":["Data","HeytingAlgebra"]}},"type":"App"},"identifier":"not"},{"annotation":{"meta":null,"sourceSpan":{"end":[0,0],"start":[0,0]}},"bindType":"NonRec","expression":{"abstraction":{"abstraction":{"annotation":{"meta":{"metaType":"IsForeign"},"sourceSpan":{"end":[133,28],"start":[133,5]}},"type":"Var","value":{"identifier":"discard","moduleName":["Control","Bind"]}},"annotation":{"meta":{"metaType":"IsSyntheticApp"},"sourceSpan":{"end":[133,28],"start":[133,5]}},"argument":{"annotation":{"meta":null,"sourceSpan":{"end":[0,0],"start":[0,0]}},"type":"Var","value":{"identifier":"discardUnit","moduleName":["Control","Bind"]}},"type":"App"},"annotation":{"meta":{"metaType":"IsSyntheticApp"},"sourceSpan":{"end":[133,28],"start":[133,5]}},"argument":{"annotation":{"meta":null,"sourceSpan":{"end":[0,0],"start":[0,0]}},"type":"Var","value":{"identifier":"bindHalogenM","moduleName":["Halogen","Query","HalogenM"]}},"type":"App"},"identifier":"discard"},{"annotation":{"meta":null,"sourceSpan":{"end":[0,0],"start":[0,0]}},"bindType":"NonRec","expression":{"abstraction":{"annotation":{"meta":{"metaType":"IsForeign"},"sourceSpan":{"end":[134,19],"start":[134,5]}},"type":"Var","value":{"identifier":"bind","moduleName":["Control","Bind"]}},"annotation":{"meta":{"metaType":"IsSyntheticApp"},"sourceSpan":{"end":[134,19],"start":[134,5]}},"argument":{"annotation":{"meta":null,"sourceSpan":{"end":[0,0],"start":[0,0]}},"type":"Var","value":{"identifier":"bindHalogenM","moduleName":["Halogen","Query","HalogenM"]}},"type":"App"},"identifier":"bind"},{"annotation":{"meta":null,"sourceSpan":{"end":[0,0],"start":[0,0]}},"bindType":"NonRec","expression":{"abstraction":{"annotation":{"meta":{"metaType":"IsForeign"},"sourceSpan":{"end":[134,19],"start":[134,14]}},"type":"Var","value":{"identifier":"get","moduleName":["Control","Monad","State","Class"]}},"annotation":{"meta":{"metaType":"IsSyntheticApp"},"sourceSpan":{"end":[134,19],"start":[134,14]}},"argument":{"annotation":{"meta":null,"sourceSpan":{"end":[0,0],"start":[0,0]}},"type":"Var","value":{"identifier":"monadStateHalogenM","moduleName":["Halogen","Query","HalogenM"]}},"type":"App"},"identifier":"get"},{"annotation":{"meta":null,"sourceSpan":{"end":[0,0],"start":[0,0]}},"bindType":"NonRec","expression":{"abstraction":{"annotation":{"meta":{"metaType":"IsForeign"},"sourceSpan":{"end":[121,61],"start":[121,57]}},"type":"Var","value":{"identifier":"show","moduleName":["Data","Show"]}},"annotation":{"meta":{"metaType":"IsSyntheticApp"},"sourceSpan":{"end":[121,65],"start":[121,57]}},"argument":{"annotation":{"meta":null,"sourceSpan":{"end":[0,0],"start":[0,0]}},"type":"Var","value":{"identifier":"showNumber","moduleName":["Data","Show"]}},"type":"App"},"identifier":"show"},{"annotation":{"meta":null,"sourceSpan":{"end":[0,0],"start":[0,0]}},"bindType":"NonRec","expression":{"abstraction":{"annotation":{"meta":{"metaType":"IsForeign"},"sourceSpan":{"end":[88,23],"start":[88,15]}},"type":"Var","value":{"identifier":"type_","moduleName":["Halogen","HTML","Properties"]}},"annotation":{"meta":{"metaType":"IsSyntheticApp"},"sourceSpan":{"end":[88,37],"start":[88,15]}},"argument":{"annotation":{"meta":null,"sourceSpan":{"end":[0,0],"start":[0,0]}},"type":"Var","value":{"identifier":"isPropInputType","moduleName":["Halogen","HTML","Core"]}},"type":"App"},"identifier":"type_"},{"annotation":{"meta":null,"sourceSpan":{"end":[0,0],"start":[0,0]}},"bindType":"NonRec","expression":{"abstraction":{"annotation":{"meta":{"metaType":"IsForeign"},"sourceSpan":{"end":[91,23],"start":[91,15]}},"type":"Var","value":{"identifier":"value","moduleName":["Halogen","HTML","Properties"]}},"annotation":{"meta":{"metaType":"IsSyntheticApp"},"sourceSpan":{"end":[91,40],"start":[91,15]}},"argument":{"annotation":{"meta":null,"sourceSpan":{"end":[0,0],"start":[0,0]}},"type":"Var","value":{"identifier":"isPropString","moduleName":["Halogen","HTML","Core"]}},"type":"App"},"identifier":"value"},{"annotation":{"meta":null,"sourceSpan":{"end":[0,0],"start":[0,0]}},"bindType":"NonRec","expression":{"abstraction":{"annotation":{"meta":{"metaType":"IsForeign"},"sourceSpan":{"end":[43,27],"start":[43,24]}},"type":"Var","value":{"identifier":"compose","moduleName":["Control","Semigroupoid"]}},"annotation":{"meta":{"metaType":"IsSyntheticApp"},"sourceSpan":{"end":[43,35],"start":[43,19]}},"argument":{"annotation":{"meta":null,"sourceSpan":{"end":[0,0],"start":[0,0]}},"type":"Var","value":{"identifier":"semigroupoidFn","moduleName":["Control","Semigroupoid"]}},"type":"App"},"identifier":"compose"},{"annotation":{"meta":null,"sourceSpan":{"end":[14,34],"start":[14,1]}},"bindType":"NonRec","expression":{"annotation":{"meta":null,"sourceSpan":{"end":[14,34],"start":[14,1]}},"constructorName":"ColorChanged","fieldNames":["value0"],"type":"Constructor","typeName":"Output"},"identifier":"ColorChanged"},{"annotation":{"meta":null,"sourceSpan":{"end":[34,18],"start":[27,1]}},"bindType":"NonRec","expression":{"annotation":{"meta":null,"sourceSpan":{"end":[34,18],"start":[27,1]}},"constructorName":"Initialize","fieldNames":[],"type":"Constructor","typeName":"Action"},"identifier":"Initialize"},{"annotation":{"meta":null,"sourceSpan":{"end":[34,18],"start":[27,1]}},"bindType":"NonRec","expression":{"annotation":{"meta":null,"sourceSpan":{"end":[34,18],"start":[27,1]}},"constructorName":"Receive","fieldNames":["value0"],"type":"Constructor","typeName":"Action"},"identifier":"Receive"},{"annotation":{"meta":null,"sourceSpan":{"end":[34,18],"start":[27,1]}},"bindType":"NonRec","expression":{"annotation":{"meta":null,"sourceSpan":{"end":[34,18],"start":[27,1]}},"constructorName":"ToggleOpen","fieldNames":[],"type":"Constructor","typeName":"Action"},"identifier":"ToggleOpen"},{"annotation":{"meta":null,"sourceSpan":{"end":[34,18],"start":[27,1]}},"bindType":"NonRec","expression":{"annotation":{"meta":null,"sourceSpan":{"end":[34,18],"start":[27,1]}},"constructorName":"SetHue","fieldNames":["value0"],"type":"Constructor","typeName":"Action"},"identifier":"SetHue"},{"annotation":{"meta":null,"sourceSpan":{"end":[34,18],"start":[27,1]}},"bindType":"NonRec","expression":{"annotation":{"meta":null,"sourceSpan":{"end":[34,18],"start":[27,1]}},"constructorName":"SetSaturation","fieldNames":["value0"],"type":"Constructor","typeName":"Action"},"identifier":"SetSaturation"},{"annotation":{"meta":null,"sourceSpan":{"end":[34,18],"start":[27,1]}},"bindType":"NonRec","expression":{"annotation":{"meta":null,"sourceSpan":{"end":[34,18],"start":[27,1]}},"constructorName":"SetLightness","fieldNames":["value0"],"type":"Constructor","typeName":"Action"},"identifier":"SetLightness"},{"annotation":{"meta":null,"sourceSpan":{"end":[34,18],"start":[27,1]}},"bindType":"NonRec","expression":{"annotation":{"meta":null,"sourceSpan":{"end":[34,18],"start":[27,1]}},"constructorName":"SetHex","fieldNames":["value0"],"type":"Constructor","typeName":"Action"},"identifier":"SetHex"},{"annotation":{"meta":null,"sourceSpan":{"end":[107,32],"start":[107,1]}},"bindType":"NonRec","expression":{"annotation":{"meta":null,"sourceSpan":{"end":[107,32],"start":[107,1]}},"argument":"color","body":{"abstraction":{"abstraction":{"annotation":{"meta":null,"sourceSpan":{"end":[0,0],"start":[0,0]}},"type":"Var","value":{"identifier":"append","moduleName":["Lattice","UI","Components","ColorPicker"]}},"annotation":{"meta":null,"sourceSpan":{"end":[110,98],"start":[109,3]}},"argument":{"annotation":{"meta":null,"sourceSpan":{"end":[109,73],"start":[109,3]}},"type":"Literal","value":{"literalType":"StringLiteral","value":"width: 24px; height: 24px; border-radius: var(--lattice-radius-sm); "}},"type":"App"},"annotation":{"meta":null,"sourceSpan":{"end":[110,98],"start":[109,3]}},"argument":{"abstraction":{"abstraction":{"annotation":{"meta":null,"sourceSpan":{"end":[0,0],"start":[0,0]}},"type":"Var","value":{"identifier":"append","moduleName":["Lattice","UI","Components","ColorPicker"]}},"annotation":{"meta":null,"sourceSpan":{"end":[110,98],"start":[109,3]}},"argument":{"annotation":{"meta":null,"sourceSpan":{"end":[110,17],"start":[110,3]}},"type":"Literal","value":{"literalType":"StringLiteral","value":"background: "}},"type":"App"},"annotation":{"meta":null,"sourceSpan":{"end":[110,98],"start":[109,3]}},"argument":{"abstraction":{"abstraction":{"annotation":{"meta":null,"sourceSpan":{"end":[0,0],"start":[0,0]}},"type":"Var","value":{"identifier":"append","moduleName":["Lattice","UI","Components","ColorPicker"]}},"annotation":{"meta":null,"sourceSpan":{"end":[110,98],"start":[109,3]}},"argument":{"annotation":{"meta":null,"sourceSpan":{"end":[110,26],"start":[110,21]}},"type":"Var","value":{"identifier":"color","sourcePos":[108,1]}},"type":"App"},"annotation":{"meta":null,"sourceSpan":{"end":[110,98],"start":[109,3]}},"argument":{"annotation":{"meta":null,"sourceSpan":{"end":[110,98],"start":[110,30]}},"type":"Literal","value":{"literalType":"StringLiteral","value":"; border: 1px solid var(--lattice-border-subtle); cursor: pointer;"}},"type":"App"},"type":"App"},"type":"App"},"type":"Abs"},"identifier":"swatchStyle"},{"annotation":{"meta":null,"sourceSpan":{"end":[112,23],"start":[112,1]}},"bindType":"NonRec","expression":{"abstraction":{"abstraction":{"annotation":{"meta":null,"sourceSpan":{"end":[0,0],"start":[0,0]}},"type":"Var","value":{"identifier":"append","moduleName":["Lattice","UI","Components","ColorPicker"]}},"annotation":{"meta":null,"sourceSpan":{"end":[116,75],"start":[114,3]}},"argument":{"annotation":{"meta":null,"sourceSpan":{"end":[114,59],"start":[114,3]}},"type":"Literal","value":{"literalType":"StringLiteral","value":"position: absolute; top: 100%; left: 0; z-index: 100; "}},"type":"App"},"annotation":{"meta":null,"sourceSpan":{"end":[116,75],"start":[114,3]}},"argument":{"abstraction":{"abstraction":{"annotation":{"meta":null,"sourceSpan":{"end":[0,0],"start":[0,0]}},"type":"Var","value":{"identifier":"append","moduleName":["Lattice","UI","Components","ColorPicker"]}},"annotation":{"meta":null,"sourceSpan":{"end":[116,75],"start":[114,3]}},"argument":{"annotation":{"meta":null,"sourceSpan":{"end":[115,84],"start":[115,3]}},"type":"Literal","value":{"literalType":"StringLiteral","value":"background: var(--lattice-surface-2); border-radius: var(--lattice-radius-md); "}},"type":"App"},"annotation":{"meta":null,"sourceSpan":{"end":[116,75],"start":[114,3]}},"argument":{"annotation":{"meta":null,"sourceSpan":{"end":[116,75],"start":[116,3]}},"type":"Literal","value":{"literalType":"StringLiteral","value":"padding: var(--lattice-space-3); box-shadow: var(--lattice-shadow-lg);"}},"type":"App"},"type":"App"},"identifier":"popoverStyle"},{"annotation":{"meta":null,"sourceSpan":{"end":[123,32],"start":[123,1]}},"bindType":"NonRec","expression":{"annotation":{"meta":null,"sourceSpan":{"end":[123,32],"start":[123,1]}},"argument":"s","body":{"annotation":{"meta":null,"sourceSpan":{"end":[125,11],"start":[125,8]}},"type":"Literal","value":{"literalType":"NumberLiteral","value":0}},"type":"Abs"},"identifier":"parseNumber"},{"annotation":{"meta":null,"sourceSpan":{"end":[47,31],"start":[47,1]}},"bindType":"NonRec","expression":{"annotation":{"meta":null,"sourceSpan":{"end":[47,31],"start":[47,1]}},"argument":"input","body":{"annotation":{"meta":null,"sourceSpan":{"end":[55,4],"start":[49,3]}},"type":"Literal","value":{"literalType":"ObjectLiteral","value":[["color",{"annotation":{"meta":null,"sourceSpan":{"end":[49,23],"start":[49,12]}},"expression":{"annotation":{"meta":null,"sourceSpan":{"end":[49,17],"start":[49,12]}},"type":"Var","value":{"identifier":"input","sourcePos":[48,1]}},"fieldName":"color","type":"Accessor"}],["label",{"annotation":{"meta":null,"sourceSpan":{"end":[50,23],"start":[50,12]}},"expression":{"annotation":{"meta":null,"sourceSpan":{"end":[50,17],"start":[50,12]}},"type":"Var","value":{"identifier":"input","sourcePos":[48,1]}},"fieldName":"label","type":"Accessor"}],["isOpen",{"annotation":{"meta":null,"sourceSpan":{"end":[51,18],"start":[51,13]}},"type":"Literal","value":{"literalType":"BooleanLiteral","value":false}}],["hue",{"annotation":{"meta":null,"sourceSpan":{"end":[52,13],"start":[52,10]}},"type":"Literal","value":{"literalType":"NumberLiteral","value":0}}],["saturation",{"annotation":{"meta":null,"sourceSpan":{"end":[53,22],"start":[53,17]}},"type":"Literal","value":{"literalType":"NumberLiteral","value":100}}],["lightness",{"annotation":{"meta":null,"sourceSpan":{"end":[54,20],"start":[54,16]}},"type":"Literal","value":{"literalType":"NumberLiteral","value":50}}]]}},"type":"Abs"},"identifier":"initialState"},{"annotation":{"meta":null,"sourceSpan":{"end":[154,49],"start":[154,1]}},"bindType":"NonRec","expression":{"annotation":{"meta":null,"sourceSpan":{"end":[154,49],"start":[154,1]}},"argument":"_h","body":{"annotation":{"meta":null,"sourceSpan":{"end":[154,49],"start":[154,1]}},"argument":"_s","body":{"annotation":{"meta":null,"sourceSpan":{"end":[154,49],"start":[154,1]}},"argument":"_l","body":{"annotation":{"meta":null,"sourceSpan":{"end":[155,30],"start":[155,21]}},"type":"Literal","value":{"literalType":"StringLiteral","value":"#808080"}},"type":"Abs"},"type":"Abs"},"type":"Abs"},"identifier":"hslToHex"},{"annotation":{"meta":null,"sourceSpan":{"end":[127,91],"start":[127,1]}},"bindType":"NonRec","expression":{"annotation":{"meta":null,"sourceSpan":{"end":[127,91],"start":[127,1]}},"argument":"dictMonadAff","body":{"annotation":{"meta":null,"sourceSpan":{"end":[152,31],"start":[128,16]}},"argument":"v","body":{"annotation":{"meta":null,"sourceSpan":{"end":[152,31],"start":[128,16]}},"caseAlternatives":[{"binders":[{"annotation":{"meta":{"constructorType":"SumType","identifiers":[],"metaType":"IsConstructor"},"sourceSpan":{"end":[129,13],"start":[129,3]}},"binderType":"ConstructorBinder","binders":[],"constructorName":{"identifier":"Initialize","moduleName":["Lattice","UI","Components","ColorPicker"]},"typeName":{"identifier":"Action","moduleName":["Lattice","UI","Components","ColorPicker"]}}],"expression":{"abstraction":{"annotation":{"meta":null,"sourceSpan":{"end":[0,0],"start":[0,0]}},"type":"Var","value":{"identifier":"pure","moduleName":["Lattice","UI","Components","ColorPicker"]}},"annotation":{"meta":null,"sourceSpan":{"end":[129,26],"start":[129,17]}},"argument":{"annotation":{"meta":{"metaType":"IsForeign"},"sourceSpan":{"end":[129,26],"start":[129,22]}},"type":"Var","value":{"identifier":"unit","moduleName":["Data","Unit"]}},"type":"App"},"isGuarded":false},{"binders":[{"annotation":{"meta":{"constructorType":"SumType","identifiers":["value0"],"metaType":"IsConstructor"},"sourceSpan":{"end":[130,16],"start":[130,3]}},"binderType":"ConstructorBinder","binders":[{"annotation":{"meta":null,"sourceSpan":{"end":[130,16],"start":[130,11]}},"binderType":"VarBinder","identifier":"input"}],"constructorName":{"identifier":"Receive","moduleName":["Lattice","UI","Components","ColorPicker"]},"typeName":{"identifier":"Action","moduleName":["Lattice","UI","Components","ColorPicker"]}}],"expression":{"abstraction":{"annotation":{"meta":null,"sourceSpan":{"end":[0,0],"start":[0,0]}},"type":"Var","value":{"identifier":"modify_","moduleName":["Lattice","UI","Components","ColorPicker"]}},"annotation":{"meta":null,"sourceSpan":{"end":[130,76],"start":[130,20]}},"argument":{"annotation":{"meta":null,"sourceSpan":{"end":[130,76],"start":[130,30]}},"argument":"v1","body":{"annotation":{"meta":null,"sourceSpan":{"end":[130,76],"start":[130,30]}},"copy":null,"expression":{"annotation":{"meta":null,"sourceSpan":{"end":[0,0],"start":[0,0]}},"type":"Var","value":{"identifier":"v1","sourcePos":[0,0]}},"type":"ObjectUpdate","updates":[["color",{"annotation":{"meta":null,"sourceSpan":{"end":[130,53],"start":[130,42]}},"expression":{"annotation":{"meta":null,"sourceSpan":{"end":[130,47],"start":[130,42]}},"type":"Var","value":{"identifier":"input","sourcePos":[130,11]}},"fieldName":"color","type":"Accessor"}],["label",{"annotation":{"meta":null,"sourceSpan":{"end":[130,74],"start":[130,63]}},"expression":{"annotation":{"meta":null,"sourceSpan":{"end":[130,68],"start":[130,63]}},"type":"Var","value":{"identifier":"input","sourcePos":[130,11]}},"fieldName":"label","type":"Accessor"}]]},"type":"Abs"},"type":"App"},"isGuarded":false},{"binders":[{"annotation":{"meta":{"constructorType":"SumType","identifiers":[],"metaType":"IsConstructor"},"sourceSpan":{"end":[131,13],"start":[131,3]}},"binderType":"ConstructorBinder","binders":[],"constructorName":{"identifier":"ToggleOpen","moduleName":["Lattice","UI","Components","ColorPicker"]},"typeName":{"identifier":"Action","moduleName":["Lattice","UI","Components","ColorPicker"]}}],"expression":{"abstraction":{"annotation":{"meta":null,"sourceSpan":{"end":[0,0],"start":[0,0]}},"type":"Var","value":{"identifier":"modify_","moduleName":["Lattice","UI","Components","ColorPicker"]}},"annotation":{"meta":null,"sourceSpan":{"end":[131,60],"start":[131,17]}},"argument":{"annotation":{"meta":null,"sourceSpan":{"end":[131,60],"start":[131,27]}},"argument":"s","body":{"annotation":{"meta":null,"sourceSpan":{"end":[131,60],"start":[131,33]}},"binds":[{"annotation":{"meta":null,"sourceSpan":{"end":[152,31],"start":[128,1]}},"bindType":"NonRec","expression":{"annotation":{"meta":null,"sourceSpan":{"end":[131,34],"start":[131,33]}},"type":"Var","value":{"identifier":"s","sourcePos":[131,28]}},"identifier":"v1"}],"expression":{"annotation":{"meta":null,"sourceSpan":{"end":[131,60],"start":[131,33]}},"copy":null,"expression":{"annotation":{"meta":null,"sourceSpan":{"end":[0,0],"start":[0,0]}},"type":"Var","value":{"identifier":"v1","sourcePos":[128,1]}},"type":"ObjectUpdate","updates":[["isOpen",{"abstraction":{"annotation":{"meta":null,"sourceSpan":{"end":[0,0],"start":[0,0]}},"type":"Var","value":{"identifier":"not","moduleName":["Lattice","UI","Components","ColorPicker"]}},"annotation":{"meta":null,"sourceSpan":{"end":[131,58],"start":[131,46]}},"argument":{"annotation":{"meta":null,"sourceSpan":{"end":[131,58],"start":[131,50]}},"expression":{"annotation":{"meta":null,"sourceSpan":{"end":[131,51],"start":[131,50]}},"type":"Var","value":{"identifier":"s","sourcePos":[131,28]}},"fieldName":"isOpen","type":"Accessor"},"type":"App"}]]},"type":"Let"},"type":"Abs"},"type":"App"},"isGuarded":false},{"binders":[{"annotation":{"meta":{"constructorType":"SumType","identifiers":["value0"],"metaType":"IsConstructor"},"sourceSpan":{"end":[132,11],"start":[132,3]}},"binderType":"ConstructorBinder","binders":[{"annotation":{"meta":null,"sourceSpan":{"end":[132,11],"start":[132,10]}},"binderType":"VarBinder","identifier":"h"}],"constructorName":{"identifier":"SetHue","moduleName":["Lattice","UI","Components","ColorPicker"]},"typeName":{"identifier":"Action","moduleName":["Lattice","UI","Components","ColorPicker"]}}],"expression":{"abstraction":{"abstraction":{"annotation":{"meta":null,"sourceSpan":{"end":[0,0],"start":[0,0]}},"type":"Var","value":{"identifier":"discard","moduleName":["Lattice","UI","Components","ColorPicker"]}},"annotation":{"meta":null,"sourceSpan":{"end":[133,28],"start":[133,5]}},"argument":{"abstraction":{"annotation":{"meta":null,"sourceSpan":{"end":[0,0],"start":[0,0]}},"type":"Var","value":{"identifier":"modify_","moduleName":["Lattice","UI","Components","ColorPicker"]}},"annotation":{"meta":null,"sourceSpan":{"end":[133,28],"start":[133,5]}},"argument":{"annotation":{"meta":null,"sourceSpan":{"end":[133,28],"start":[133,15]}},"argument":"v1","body":{"annotation":{"meta":null,"sourceSpan":{"end":[133,28],"start":[133,15]}},"copy":null,"expression":{"annotation":{"meta":null,"sourceSpan":{"end":[0,0],"start":[0,0]}},"type":"Var","value":{"identifier":"v1","sourcePos":[0,0]}},"type":"ObjectUpdate","updates":[["hue",{"annotation":{"meta":null,"sourceSpan":{"end":[133,26],"start":[133,25]}},"type":"Var","value":{"identifier":"h","sourcePos":[132,10]}}]]},"type":"Abs"},"type":"App"},"type":"App"},"annotation":{"meta":null,"sourceSpan":{"end":[133,28],"start":[133,5]}},"argument":{"annotation":{"meta":null,"sourceSpan":{"end":[133,28],"start":[133,5]}},"argument":"$__unused","body":{"abstraction":{"abstraction":{"annotation":{"meta":null,"sourceSpan":{"end":[0,0],"start":[0,0]}},"type":"Var","value":{"identifier":"bind","moduleName":["Lattice","UI","Components","ColorPicker"]}},"annotation":{"meta":null,"sourceSpan":{"end":[134,19],"start":[134,5]}},"argument":{"annotation":{"meta":null,"sourceSpan":{"end":[0,0],"start":[0,0]}},"type":"Var","value":{"identifier":"get","moduleName":["Lattice","UI","Components","ColorPicker"]}},"type":"App"},"annotation":{"meta":null,"sourceSpan":{"end":[134,19],"start":[134,5]}},"argument":{"annotation":{"meta":null,"sourceSpan":{"end":[134,19],"start":[134,5]}},"argument":"state","body":{"annotation":{"meta":null,"sourceSpan":{"end":[135,71],"start":[135,5]}},"binds":[{"annotation":{"meta":null,"sourceSpan":{"end":[135,71],"start":[135,9]}},"bindType":"NonRec","expression":{"abstraction":{"abstraction":{"abstraction":{"annotation":{"meta":null,"sourceSpan":{"end":[135,28],"start":[135,20]}},"type":"Var","value":{"identifier":"hslToHex","moduleName":["Lattice","UI","Components","ColorPicker"]}},"annotation":{"meta":null,"sourceSpan":{"end":[135,38],"start":[135,20]}},"argument":{"annotation":{"meta":null,"sourceSpan":{"end":[135,38],"start":[135,29]}},"expression":{"annotation":{"meta":null,"sourceSpan":{"end":[135,34],"start":[135,29]}},"type":"Var","value":{"identifier":"state","sourcePos":[134,5]}},"fieldName":"hue","type":"Accessor"},"type":"App"},"annotation":{"meta":null,"sourceSpan":{"end":[135,55],"start":[135,20]}},"argument":{"annotation":{"meta":null,"sourceSpan":{"end":[135,55],"start":[135,39]}},"expression":{"annotation":{"meta":null,"sourceSpan":{"end":[135,44],"start":[135,39]}},"type":"Var","value":{"identifier":"state","sourcePos":[134,5]}},"fieldName":"saturation","type":"Accessor"},"type":"App"},"annotation":{"meta":null,"sourceSpan":{"end":[135,71],"start":[135,20]}},"argument":{"annotation":{"meta":null,"sourceSpan":{"end":[135,71],"start":[135,56]}},"expression":{"annotation":{"meta":null,"sourceSpan":{"end":[135,61],"start":[135,56]}},"type":"Var","value":{"identifier":"state","sourcePos":[134,5]}},"fieldName":"lightness","type":"Accessor"},"type":"App"},"identifier":"newColor"}],"expression":{"abstraction":{"abstraction":{"annotation":{"meta":null,"sourceSpan":{"end":[0,0],"start":[0,0]}},"type":"Var","value":{"identifier":"discard","moduleName":["Lattice","UI","Components","ColorPicker"]}},"annotation":{"meta":null,"sourceSpan":{"end":[136,37],"start":[136,5]}},"argument":{"abstraction":{"annotation":{"meta":null,"sourceSpan":{"end":[0,0],"start":[0,0]}},"type":"Var","value":{"identifier":"modify_","moduleName":["Lattice","UI","Components","ColorPicker"]}},"annotation":{"meta":null,"sourceSpan":{"end":[136,37],"start":[136,5]}},"argument":{"annotation":{"meta":null,"sourceSpan":{"end":[136,37],"start":[136,15]}},"argument":"v1","body":{"annotation":{"meta":null,"sourceSpan":{"end":[136,37],"start":[136,15]}},"copy":null,"expression":{"annotation":{"meta":null,"sourceSpan":{"end":[0,0],"start":[0,0]}},"type":"Var","value":{"identifier":"v1","sourcePos":[0,0]}},"type":"ObjectUpdate","updates":[["color",{"annotation":{"meta":null,"sourceSpan":{"end":[136,35],"start":[136,27]}},"type":"Var","value":{"identifier":"newColor","sourcePos":[135,9]}}]]},"type":"Abs"},"type":"App"},"type":"App"},"annotation":{"meta":null,"sourceSpan":{"end":[136,37],"start":[136,5]}},"argument":{"annotation":{"meta":null,"sourceSpan":{"end":[136,37],"start":[136,5]}},"argument":"$__unused","body":{"abstraction":{"annotation":{"meta":{"metaType":"IsForeign"},"sourceSpan":{"end":[137,12],"start":[137,5]}},"type":"Var","value":{"identifier":"raise","moduleName":["Halogen","Query","HalogenM"]}},"annotation":{"meta":null,"sourceSpan":{"end":[137,36],"start":[137,5]}},"argument":{"abstraction":{"annotation":{"meta":{"constructorType":"ProductType","identifiers":["value0"],"metaType":"IsConstructor"},"sourceSpan":{"end":[137,26],"start":[137,14]}},"type":"Var","value":{"identifier":"ColorChanged","moduleName":["Lattice","UI","Components","ColorPicker"]}},"annotation":{"meta":null,"sourceSpan":{"end":[137,35],"start":[137,14]}},"argument":{"annotation":{"meta":null,"sourceSpan":{"end":[137,35],"start":[137,27]}},"type":"Var","value":{"identifier":"newColor","sourcePos":[135,9]}},"type":"App"},"type":"App"},"type":"Abs"},"type":"App"},"type":"Let"},"type":"Abs"},"type":"App"},"type":"Abs"},"type":"App"},"isGuarded":false},{"binders":[{"annotation":{"meta":{"constructorType":"SumType","identifiers":["value0"],"metaType":"IsConstructor"},"sourceSpan":{"end":[138,18],"start":[138,3]}},"binderType":"ConstructorBinder","binders":[{"annotation":{"meta":null,"sourceSpan":{"end":[138,18],"start":[138,17]}},"binderType":"VarBinder","identifier":"s"}],"constructorName":{"identifier":"SetSaturation","moduleName":["Lattice","UI","Components","ColorPicker"]},"typeName":{"identifier":"Action","moduleName":["Lattice","UI","Components","ColorPicker"]}}],"expression":{"abstraction":{"abstraction":{"annotation":{"meta":null,"sourceSpan":{"end":[0,0],"start":[0,0]}},"type":"Var","value":{"identifier":"discard","moduleName":["Lattice","UI","Components","ColorPicker"]}},"annotation":{"meta":null,"sourceSpan":{"end":[139,35],"start":[139,5]}},"argument":{"abstraction":{"annotation":{"meta":null,"sourceSpan":{"end":[0,0],"start":[0,0]}},"type":"Var","value":{"identifier":"modify_","moduleName":["Lattice","UI","Components","ColorPicker"]}},"annotation":{"meta":null,"sourceSpan":{"end":[139,35],"start":[139,5]}},"argument":{"annotation":{"meta":null,"sourceSpan":{"end":[139,35],"start":[139,15]}},"argument":"v1","body":{"annotation":{"meta":null,"sourceSpan":{"end":[139,35],"start":[139,15]}},"copy":null,"expression":{"annotation":{"meta":null,"sourceSpan":{"end":[0,0],"start":[0,0]}},"type":"Var","value":{"identifier":"v1","sourcePos":[0,0]}},"type":"ObjectUpdate","updates":[["saturation",{"annotation":{"meta":null,"sourceSpan":{"end":[139,33],"start":[139,32]}},"type":"Var","value":{"identifier":"s","sourcePos":[138,17]}}]]},"type":"Abs"},"type":"App"},"type":"App"},"annotation":{"meta":null,"sourceSpan":{"end":[139,35],"start":[139,5]}},"argument":{"annotation":{"meta":null,"sourceSpan":{"end":[139,35],"start":[139,5]}},"argument":"$__unused","body":{"abstraction":{"abstraction":{"annotation":{"meta":null,"sourceSpan":{"end":[0,0],"start":[0,0]}},"type":"Var","value":{"identifier":"bind","moduleName":["Lattice","UI","Components","ColorPicker"]}},"annotation":{"meta":null,"sourceSpan":{"end":[140,19],"start":[140,5]}},"argument":{"annotation":{"meta":null,"sourceSpan":{"end":[0,0],"start":[0,0]}},"type":"Var","value":{"identifier":"get","moduleName":["Lattice","UI","Components","ColorPicker"]}},"type":"App"},"annotation":{"meta":null,"sourceSpan":{"end":[140,19],"start":[140,5]}},"argument":{"annotation":{"meta":null,"sourceSpan":{"end":[140,19],"start":[140,5]}},"argument":"state","body":{"annotation":{"meta":null,"sourceSpan":{"end":[141,71],"start":[141,5]}},"binds":[{"annotation":{"meta":null,"sourceSpan":{"end":[141,71],"start":[141,9]}},"bindType":"NonRec","expression":{"abstraction":{"abstraction":{"abstraction":{"annotation":{"meta":null,"sourceSpan":{"end":[141,28],"start":[141,20]}},"type":"Var","value":{"identifier":"hslToHex","moduleName":["Lattice","UI","Components","ColorPicker"]}},"annotation":{"meta":null,"sourceSpan":{"end":[141,38],"start":[141,20]}},"argument":{"annotation":{"meta":null,"sourceSpan":{"end":[141,38],"start":[141,29]}},"expression":{"annotation":{"meta":null,"sourceSpan":{"end":[141,34],"start":[141,29]}},"type":"Var","value":{"identifier":"state","sourcePos":[140,5]}},"fieldName":"hue","type":"Accessor"},"type":"App"},"annotation":{"meta":null,"sourceSpan":{"end":[141,55],"start":[141,20]}},"argument":{"annotation":{"meta":null,"sourceSpan":{"end":[141,55],"start":[141,39]}},"expression":{"annotation":{"meta":null,"sourceSpan":{"end":[141,44],"start":[141,39]}},"type":"Var","value":{"identifier":"state","sourcePos":[140,5]}},"fieldName":"saturation","type":"Accessor"},"type":"App"},"annotation":{"meta":null,"sourceSpan":{"end":[141,71],"start":[141,20]}},"argument":{"annotation":{"meta":null,"sourceSpan":{"end":[141,71],"start":[141,56]}},"expression":{"annotation":{"meta":null,"sourceSpan":{"end":[141,61],"start":[141,56]}},"type":"Var","value":{"identifier":"state","sourcePos":[140,5]}},"fieldName":"lightness","type":"Accessor"},"type":"App"},"identifier":"newColor"}],"expression":{"abstraction":{"abstraction":{"annotation":{"meta":null,"sourceSpan":{"end":[0,0],"start":[0,0]}},"type":"Var","value":{"identifier":"discard","moduleName":["Lattice","UI","Components","ColorPicker"]}},"annotation":{"meta":null,"sourceSpan":{"end":[142,37],"start":[142,5]}},"argument":{"abstraction":{"annotation":{"meta":null,"sourceSpan":{"end":[0,0],"start":[0,0]}},"type":"Var","value":{"identifier":"modify_","moduleName":["Lattice","UI","Components","ColorPicker"]}},"annotation":{"meta":null,"sourceSpan":{"end":[142,37],"start":[142,5]}},"argument":{"annotation":{"meta":null,"sourceSpan":{"end":[142,37],"start":[142,15]}},"argument":"v1","body":{"annotation":{"meta":null,"sourceSpan":{"end":[142,37],"start":[142,15]}},"copy":null,"expression":{"annotation":{"meta":null,"sourceSpan":{"end":[0,0],"start":[0,0]}},"type":"Var","value":{"identifier":"v1","sourcePos":[0,0]}},"type":"ObjectUpdate","updates":[["color",{"annotation":{"meta":null,"sourceSpan":{"end":[142,35],"start":[142,27]}},"type":"Var","value":{"identifier":"newColor","sourcePos":[141,9]}}]]},"type":"Abs"},"type":"App"},"type":"App"},"annotation":{"meta":null,"sourceSpan":{"end":[142,37],"start":[142,5]}},"argument":{"annotation":{"meta":null,"sourceSpan":{"end":[142,37],"start":[142,5]}},"argument":"$__unused","body":{"abstraction":{"annotation":{"meta":{"metaType":"IsForeign"},"sourceSpan":{"end":[143,12],"start":[143,5]}},"type":"Var","value":{"identifier":"raise","moduleName":["Halogen","Query","HalogenM"]}},"annotation":{"meta":null,"sourceSpan":{"end":[143,36],"start":[143,5]}},"argument":{"abstraction":{"annotation":{"meta":{"constructorType":"ProductType","identifiers":["value0"],"metaType":"IsConstructor"},"sourceSpan":{"end":[143,26],"start":[143,14]}},"type":"Var","value":{"identifier":"ColorChanged","moduleName":["Lattice","UI","Components","ColorPicker"]}},"annotation":{"meta":null,"sourceSpan":{"end":[143,35],"start":[143,14]}},"argument":{"annotation":{"meta":null,"sourceSpan":{"end":[143,35],"start":[143,27]}},"type":"Var","value":{"identifier":"newColor","sourcePos":[141,9]}},"type":"App"},"type":"App"},"type":"Abs"},"type":"App"},"type":"Let"},"type":"Abs"},"type":"App"},"type":"Abs"},"type":"App"},"isGuarded":false},{"binders":[{"annotation":{"meta":{"constructorType":"SumType","identifiers":["value0"],"metaType":"IsConstructor"},"sourceSpan":{"end":[144,17],"start":[144,3]}},"binderType":"ConstructorBinder","binders":[{"annotation":{"meta":null,"sourceSpan":{"end":[144,17],"start":[144,16]}},"binderType":"VarBinder","identifier":"l"}],"constructorName":{"identifier":"SetLightness","moduleName":["Lattice","UI","Components","ColorPicker"]},"typeName":{"identifier":"Action","moduleName":["Lattice","UI","Components","ColorPicker"]}}],"expression":{"abstraction":{"abstraction":{"annotation":{"meta":null,"sourceSpan":{"end":[0,0],"start":[0,0]}},"type":"Var","value":{"identifier":"discard","moduleName":["Lattice","UI","Components","ColorPicker"]}},"annotation":{"meta":null,"sourceSpan":{"end":[145,34],"start":[145,5]}},"argument":{"abstraction":{"annotation":{"meta":null,"sourceSpan":{"end":[0,0],"start":[0,0]}},"type":"Var","value":{"identifier":"modify_","moduleName":["Lattice","UI","Components","ColorPicker"]}},"annotation":{"meta":null,"sourceSpan":{"end":[145,34],"start":[145,5]}},"argument":{"annotation":{"meta":null,"sourceSpan":{"end":[145,34],"start":[145,15]}},"argument":"v1","body":{"annotation":{"meta":null,"sourceSpan":{"end":[145,34],"start":[145,15]}},"copy":null,"expression":{"annotation":{"meta":null,"sourceSpan":{"end":[0,0],"start":[0,0]}},"type":"Var","value":{"identifier":"v1","sourcePos":[0,0]}},"type":"ObjectUpdate","updates":[["lightness",{"annotation":{"meta":null,"sourceSpan":{"end":[145,32],"start":[145,31]}},"type":"Var","value":{"identifier":"l","sourcePos":[144,16]}}]]},"type":"Abs"},"type":"App"},"type":"App"},"annotation":{"meta":null,"sourceSpan":{"end":[145,34],"start":[145,5]}},"argument":{"annotation":{"meta":null,"sourceSpan":{"end":[145,34],"start":[145,5]}},"argument":"$__unused","body":{"abstraction":{"abstraction":{"annotation":{"meta":null,"sourceSpan":{"end":[0,0],"start":[0,0]}},"type":"Var","value":{"identifier":"bind","moduleName":["Lattice","UI","Components","ColorPicker"]}},"annotation":{"meta":null,"sourceSpan":{"end":[146,19],"start":[146,5]}},"argument":{"annotation":{"meta":null,"sourceSpan":{"end":[0,0],"start":[0,0]}},"type":"Var","value":{"identifier":"get","moduleName":["Lattice","UI","Components","ColorPicker"]}},"type":"App"},"annotation":{"meta":null,"sourceSpan":{"end":[146,19],"start":[146,5]}},"argument":{"annotation":{"meta":null,"sourceSpan":{"end":[146,19],"start":[146,5]}},"argument":"state","body":{"annotation":{"meta":null,"sourceSpan":{"end":[147,71],"start":[147,5]}},"binds":[{"annotation":{"meta":null,"sourceSpan":{"end":[147,71],"start":[147,9]}},"bindType":"NonRec","expression":{"abstraction":{"abstraction":{"abstraction":{"annotation":{"meta":null,"sourceSpan":{"end":[147,28],"start":[147,20]}},"type":"Var","value":{"identifier":"hslToHex","moduleName":["Lattice","UI","Components","ColorPicker"]}},"annotation":{"meta":null,"sourceSpan":{"end":[147,38],"start":[147,20]}},"argument":{"annotation":{"meta":null,"sourceSpan":{"end":[147,38],"start":[147,29]}},"expression":{"annotation":{"meta":null,"sourceSpan":{"end":[147,34],"start":[147,29]}},"type":"Var","value":{"identifier":"state","sourcePos":[146,5]}},"fieldName":"hue","type":"Accessor"},"type":"App"},"annotation":{"meta":null,"sourceSpan":{"end":[147,55],"start":[147,20]}},"argument":{"annotation":{"meta":null,"sourceSpan":{"end":[147,55],"start":[147,39]}},"expression":{"annotation":{"meta":null,"sourceSpan":{"end":[147,44],"start":[147,39]}},"type":"Var","value":{"identifier":"state","sourcePos":[146,5]}},"fieldName":"saturation","type":"Accessor"},"type":"App"},"annotation":{"meta":null,"sourceSpan":{"end":[147,71],"start":[147,20]}},"argument":{"annotation":{"meta":null,"sourceSpan":{"end":[147,71],"start":[147,56]}},"expression":{"annotation":{"meta":null,"sourceSpan":{"end":[147,61],"start":[147,56]}},"type":"Var","value":{"identifier":"state","sourcePos":[146,5]}},"fieldName":"lightness","type":"Accessor"},"type":"App"},"identifier":"newColor"}],"expression":{"abstraction":{"abstraction":{"annotation":{"meta":null,"sourceSpan":{"end":[0,0],"start":[0,0]}},"type":"Var","value":{"identifier":"discard","moduleName":["Lattice","UI","Components","ColorPicker"]}},"annotation":{"meta":null,"sourceSpan":{"end":[148,37],"start":[148,5]}},"argument":{"abstraction":{"annotation":{"meta":null,"sourceSpan":{"end":[0,0],"start":[0,0]}},"type":"Var","value":{"identifier":"modify_","moduleName":["Lattice","UI","Components","ColorPicker"]}},"annotation":{"meta":null,"sourceSpan":{"end":[148,37],"start":[148,5]}},"argument":{"annotation":{"meta":null,"sourceSpan":{"end":[148,37],"start":[148,15]}},"argument":"v1","body":{"annotation":{"meta":null,"sourceSpan":{"end":[148,37],"start":[148,15]}},"copy":null,"expression":{"annotation":{"meta":null,"sourceSpan":{"end":[0,0],"start":[0,0]}},"type":"Var","value":{"identifier":"v1","sourcePos":[0,0]}},"type":"ObjectUpdate","updates":[["color",{"annotation":{"meta":null,"sourceSpan":{"end":[148,35],"start":[148,27]}},"type":"Var","value":{"identifier":"newColor","sourcePos":[147,9]}}]]},"type":"Abs"},"type":"App"},"type":"App"},"annotation":{"meta":null,"sourceSpan":{"end":[148,37],"start":[148,5]}},"argument":{"annotation":{"meta":null,"sourceSpan":{"end":[148,37],"start":[148,5]}},"argument":"$__unused","body":{"abstraction":{"annotation":{"meta":{"metaType":"IsForeign"},"sourceSpan":{"end":[149,12],"start":[149,5]}},"type":"Var","value":{"identifier":"raise","moduleName":["Halogen","Query","HalogenM"]}},"annotation":{"meta":null,"sourceSpan":{"end":[149,36],"start":[149,5]}},"argument":{"abstraction":{"annotation":{"meta":{"constructorType":"ProductType","identifiers":["value0"],"metaType":"IsConstructor"},"sourceSpan":{"end":[149,26],"start":[149,14]}},"type":"Var","value":{"identifier":"ColorChanged","moduleName":["Lattice","UI","Components","ColorPicker"]}},"annotation":{"meta":null,"sourceSpan":{"end":[149,35],"start":[149,14]}},"argument":{"annotation":{"meta":null,"sourceSpan":{"end":[149,35],"start":[149,27]}},"type":"Var","value":{"identifier":"newColor","sourcePos":[147,9]}},"type":"App"},"type":"App"},"type":"Abs"},"type":"App"},"type":"Let"},"type":"Abs"},"type":"App"},"type":"Abs"},"type":"App"},"isGuarded":false},{"binders":[{"annotation":{"meta":{"constructorType":"SumType","identifiers":["value0"],"metaType":"IsConstructor"},"sourceSpan":{"end":[150,13],"start":[150,3]}},"binderType":"ConstructorBinder","binders":[{"annotation":{"meta":null,"sourceSpan":{"end":[150,13],"start":[150,10]}},"binderType":"VarBinder","identifier":"hex"}],"constructorName":{"identifier":"SetHex","moduleName":["Lattice","UI","Components","ColorPicker"]},"typeName":{"identifier":"Action","moduleName":["Lattice","UI","Components","ColorPicker"]}}],"expression":{"abstraction":{"abstraction":{"annotation":{"meta":null,"sourceSpan":{"end":[0,0],"start":[0,0]}},"type":"Var","value":{"identifier":"discard","moduleName":["Lattice","UI","Components","ColorPicker"]}},"annotation":{"meta":null,"sourceSpan":{"end":[151,32],"start":[151,5]}},"argument":{"abstraction":{"annotation":{"meta":null,"sourceSpan":{"end":[0,0],"start":[0,0]}},"type":"Var","value":{"identifier":"modify_","moduleName":["Lattice","UI","Components","ColorPicker"]}},"annotation":{"meta":null,"sourceSpan":{"end":[151,32],"start":[151,5]}},"argument":{"annotation":{"meta":null,"sourceSpan":{"end":[151,32],"start":[151,15]}},"argument":"v1","body":{"annotation":{"meta":null,"sourceSpan":{"end":[151,32],"start":[151,15]}},"copy":null,"expression":{"annotation":{"meta":null,"sourceSpan":{"end":[0,0],"start":[0,0]}},"type":"Var","value":{"identifier":"v1","sourcePos":[0,0]}},"type":"ObjectUpdate","updates":[["color",{"annotation":{"meta":null,"sourceSpan":{"end":[151,30],"start":[151,27]}},"type":"Var","value":{"identifier":"hex","sourcePos":[150,10]}}]]},"type":"Abs"},"type":"App"},"type":"App"},"annotation":{"meta":null,"sourceSpan":{"end":[151,32],"start":[151,5]}},"argument":{"annotation":{"meta":null,"sourceSpan":{"end":[151,32],"start":[151,5]}},"argument":"$__unused","body":{"abstraction":{"annotation":{"meta":{"metaType":"IsForeign"},"sourceSpan":{"end":[152,12],"start":[152,5]}},"type":"Var","value":{"identifier":"raise","moduleName":["Halogen","Query","HalogenM"]}},"annotation":{"meta":null,"sourceSpan":{"end":[152,31],"start":[152,5]}},"argument":{"abstraction":{"annotation":{"meta":{"constructorType":"ProductType","identifiers":["value0"],"metaType":"IsConstructor"},"sourceSpan":{"end":[152,26],"start":[152,14]}},"type":"Var","value":{"identifier":"ColorChanged","moduleName":["Lattice","UI","Components","ColorPicker"]}},"annotation":{"meta":null,"sourceSpan":{"end":[152,30],"start":[152,14]}},"argument":{"annotation":{"meta":null,"sourceSpan":{"end":[152,30],"start":[152,27]}},"type":"Var","value":{"identifier":"hex","sourcePos":[150,10]}},"type":"App"},"type":"App"},"type":"Abs"},"type":"App"},"isGuarded":false}],"caseExpressions":[{"annotation":{"meta":null,"sourceSpan":{"end":[0,0],"start":[0,0]}},"type":"Var","value":{"identifier":"v","sourcePos":[0,0]}}],"type":"Case"},"type":"Abs"},"type":"Abs"},"identifier":"handleAction"},{"annotation":{"meta":null,"sourceSpan":{"end":[118,34],"start":[118,1]}},"bindType":"NonRec","expression":{"annotation":{"meta":null,"sourceSpan":{"end":[118,34],"start":[118,1]}},"argument":"hue","body":{"abstraction":{"abstraction":{"annotation":{"meta":null,"sourceSpan":{"end":[0,0],"start":[0,0]}},"type":"Var","value":{"identifier":"append","moduleName":["Lattice","UI","Components","ColorPicker"]}},"annotation":{"meta":null,"sourceSpan":{"end":[121,85],"start":[120,3]}},"argument":{"annotation":{"meta":null,"sourceSpan":{"end":[120,34],"start":[120,3]}},"type":"Literal","value":{"literalType":"StringLiteral","value":"width: 200px; height: 150px; "}},"type":"App"},"annotation":{"meta":null,"sourceSpan":{"end":[121,85],"start":[120,3]}},"argument":{"abstraction":{"abstraction":{"annotation":{"meta":null,"sourceSpan":{"end":[0,0],"start":[0,0]}},"type":"Var","value":{"identifier":"append","moduleName":["Lattice","UI","Components","ColorPicker"]}},"annotation":{"meta":null,"sourceSpan":{"end":[121,85],"start":[120,3]}},"argument":{"annotation":{"meta":null,"sourceSpan":{"end":[121,53],"start":[121,3]}},"type":"Literal","value":{"literalType":"StringLiteral","value":"background: linear-gradient(to right, #fff, hsl("}},"type":"App"},"annotation":{"meta":null,"sourceSpan":{"end":[121,85],"start":[120,3]}},"argument":{"abstraction":{"abstraction":{"annotation":{"meta":null,"sourceSpan":{"end":[0,0],"start":[0,0]}},"type":"Var","value":{"identifier":"append","moduleName":["Lattice","UI","Components","ColorPicker"]}},"annotation":{"meta":null,"sourceSpan":{"end":[121,85],"start":[120,3]}},"argument":{"abstraction":{"annotation":{"meta":null,"sourceSpan":{"end":[0,0],"start":[0,0]}},"type":"Var","value":{"identifier":"show","moduleName":["Lattice","UI","Components","ColorPicker"]}},"annotation":{"meta":null,"sourceSpan":{"end":[121,65],"start":[121,57]}},"argument":{"annotation":{"meta":null,"sourceSpan":{"end":[121,65],"start":[121,62]}},"type":"Var","value":{"identifier":"hue","sourcePos":[119,1]}},"type":"App"},"type":"App"},"annotation":{"meta":null,"sourceSpan":{"end":[121,85],"start":[120,3]}},"argument":{"annotation":{"meta":null,"sourceSpan":{"end":[121,85],"start":[121,69]}},"type":"Literal","value":{"literalType":"StringLiteral","value":", 100%, 50%));"}},"type":"App"},"type":"App"},"type":"App"},"type":"Abs"},"identifier":"gradientStyle"},{"annotation":{"meta":null,"sourceSpan":{"end":[73,64],"start":[73,1]}},"bindType":"NonRec","expression":{"annotation":{"meta":null,"sourceSpan":{"end":[73,64],"start":[73,1]}},"argument":"state","body":{"abstraction":{"abstraction":{"annotation":{"meta":{"metaType":"IsForeign"},"sourceSpan":{"end":[75,9],"start":[75,3]}},"type":"Var","value":{"identifier":"div","moduleName":["Halogen","HTML","Elements"]}},"annotation":{"meta":null,"sourceSpan":{"end":[78,6],"start":[75,3]}},"argument":{"annotation":{"meta":null,"sourceSpan":{"end":[78,6],"start":[76,5]}},"type":"Literal","value":{"literalType":"ArrayLiteral","value":[{"abstraction":{"annotation":{"meta":{"metaType":"IsForeign"},"sourceSpan":{"end":[76,10],"start":[76,7]}},"type":"Var","value":{"identifier":"cls","moduleName":["Lattice","UI","Core"]}},"annotation":{"meta":null,"sourceSpan":{"end":[76,38],"start":[76,7]}},"argument":{"annotation":{"meta":null,"sourceSpan":{"end":[76,38],"start":[76,11]}},"type":"Literal","value":{"literalType":"ArrayLiteral","value":[{"annotation":{"meta":null,"sourceSpan":{"end":[76,36],"start":[76,13]}},"type":"Literal","value":{"literalType":"StringLiteral","value":"lattice-color-popover"}}]}},"type":"App"},{"abstraction":{"abstraction":{"annotation":{"meta":{"metaType":"IsForeign"},"sourceSpan":{"end":[77,14],"start":[77,7]}},"type":"Var","value":{"identifier":"attr","moduleName":["Halogen","HTML","Properties"]}},"annotation":{"meta":null,"sourceSpan":{"end":[77,36],"start":[77,7]}},"argument":{"abstraction":{"annotation":{"meta":{"metaType":"IsNewtype"},"sourceSpan":{"end":[77,27],"start":[77,16]}},"type":"Var","value":{"identifier":"AttrName","moduleName":["Web","HTML","Common"]}},"annotation":{"meta":null,"sourceSpan":{"end":[77,35],"start":[77,16]}},"argument":{"annotation":{"meta":null,"sourceSpan":{"end":[77,35],"start":[77,28]}},"type":"Literal","value":{"literalType":"StringLiteral","value":"style"}},"type":"App"},"type":"App"},"annotation":{"meta":null,"sourceSpan":{"end":[77,49],"start":[77,7]}},"argument":{"annotation":{"meta":null,"sourceSpan":{"end":[77,49],"start":[77,37]}},"type":"Var","value":{"identifier":"popoverStyle","moduleName":["Lattice","UI","Components","ColorPicker"]}},"type":"App"}]}},"type":"App"},"annotation":{"meta":null,"sourceSpan":{"end":[102,6],"start":[75,3]}},"argument":{"annotation":{"meta":null,"sourceSpan":{"end":[102,6],"start":[79,5]}},"type":"Literal","value":{"literalType":"ArrayLiteral","value":[{"abstraction":{"abstraction":{"annotation":{"meta":{"metaType":"IsForeign"},"sourceSpan":{"end":[79,13],"start":[79,7]}},"type":"Var","value":{"identifier":"div","moduleName":["Halogen","HTML","Elements"]}},"annotation":{"meta":null,"sourceSpan":{"end":[79,50],"start":[79,7]}},"argument":{"annotation":{"meta":null,"sourceSpan":{"end":[79,50],"start":[79,14]}},"type":"Literal","value":{"literalType":"ArrayLiteral","value":[{"abstraction":{"annotation":{"meta":{"metaType":"IsForeign"},"sourceSpan":{"end":[79,19],"start":[79,16]}},"type":"Var","value":{"identifier":"cls","moduleName":["Lattice","UI","Core"]}},"annotation":{"meta":null,"sourceSpan":{"end":[79,48],"start":[79,16]}},"argument":{"annotation":{"meta":null,"sourceSpan":{"end":[79,48],"start":[79,20]}},"type":"Literal","value":{"literalType":"ArrayLiteral","value":[{"annotation":{"meta":null,"sourceSpan":{"end":[79,46],"start":[79,22]}},"type":"Literal","value":{"literalType":"StringLiteral","value":"lattice-color-gradient"}}]}},"type":"App"}]}},"type":"App"},"annotation":{"meta":null,"sourceSpan":{"end":[85,10],"start":[79,7]}},"argument":{"annotation":{"meta":null,"sourceSpan":{"end":[85,10],"start":[80,9]}},"type":"Literal","value":{"literalType":"ArrayLiteral","value":[{"abstraction":{"abstraction":{"annotation":{"meta":{"metaType":"IsForeign"},"sourceSpan":{"end":[80,17],"start":[80,11]}},"type":"Var","value":{"identifier":"div","moduleName":["Halogen","HTML","Elements"]}},"annotation":{"meta":null,"sourceSpan":{"end":[83,14],"start":[80,11]}},"argument":{"annotation":{"meta":null,"sourceSpan":{"end":[83,14],"start":[81,13]}},"type":"Literal","value":{"literalType":"ArrayLiteral","value":[{"abstraction":{"annotation":{"meta":{"metaType":"IsForeign"},"sourceSpan":{"end":[81,18],"start":[81,15]}},"type":"Var","value":{"identifier":"cls","moduleName":["Lattice","UI","Core"]}},"annotation":{"meta":null,"sourceSpan":{"end":[81,49],"start":[81,15]}},"argument":{"annotation":{"meta":null,"sourceSpan":{"end":[81,49],"start":[81,19]}},"type":"Literal","value":{"literalType":"ArrayLiteral","value":[{"annotation":{"meta":null,"sourceSpan":{"end":[81,47],"start":[81,21]}},"type":"Literal","value":{"literalType":"StringLiteral","value":"lattice-color-saturation"}}]}},"type":"App"},{"abstraction":{"abstraction":{"annotation":{"meta":{"metaType":"IsForeign"},"sourceSpan":{"end":[82,22],"start":[82,15]}},"type":"Var","value":{"identifier":"attr","moduleName":["Halogen","HTML","Properties"]}},"annotation":{"meta":null,"sourceSpan":{"end":[82,44],"start":[82,15]}},"argument":{"abstraction":{"annotation":{"meta":{"metaType":"IsNewtype"},"sourceSpan":{"end":[82,35],"start":[82,24]}},"type":"Var","value":{"identifier":"AttrName","moduleName":["Web","HTML","Common"]}},"annotation":{"meta":null,"sourceSpan":{"end":[82,43],"start":[82,24]}},"argument":{"annotation":{"meta":null,"sourceSpan":{"end":[82,43],"start":[82,36]}},"type":"Literal","value":{"literalType":"StringLiteral","value":"style"}},"type":"App"},"type":"App"},"annotation":{"meta":null,"sourceSpan":{"end":[82,70],"start":[82,15]}},"argument":{"abstraction":{"annotation":{"meta":null,"sourceSpan":{"end":[82,59],"start":[82,46]}},"type":"Var","value":{"identifier":"gradientStyle","moduleName":["Lattice","UI","Components","ColorPicker"]}},"annotation":{"meta":null,"sourceSpan":{"end":[82,69],"start":[82,46]}},"argument":{"annotation":{"meta":null,"sourceSpan":{"end":[82,69],"start":[82,60]}},"expression":{"annotation":{"meta":null,"sourceSpan":{"end":[82,65],"start":[82,60]}},"type":"Var","value":{"identifier":"state","sourcePos":[74,1]}},"fieldName":"hue","type":"Accessor"},"type":"App"},"type":"App"}]}},"type":"App"},"annotation":{"meta":null,"sourceSpan":{"end":[84,15],"start":[80,11]}},"argument":{"annotation":{"meta":null,"sourceSpan":{"end":[84,15],"start":[84,13]}},"type":"Literal","value":{"literalType":"ArrayLiteral","value":[]}},"type":"App"}]}},"type":"App"},{"abstraction":{"abstraction":{"annotation":{"meta":{"metaType":"IsForeign"},"sourceSpan":{"end":[86,13],"start":[86,7]}},"type":"Var","value":{"identifier":"div","moduleName":["Halogen","HTML","Elements"]}},"annotation":{"meta":null,"sourceSpan":{"end":[86,52],"start":[86,7]}},"argument":{"annotation":{"meta":null,"sourceSpan":{"end":[86,52],"start":[86,14]}},"type":"Literal","value":{"literalType":"ArrayLiteral","value":[{"abstraction":{"annotation":{"meta":{"metaType":"IsForeign"},"sourceSpan":{"end":[86,19],"start":[86,16]}},"type":"Var","value":{"identifier":"cls","moduleName":["Lattice","UI","Core"]}},"annotation":{"meta":null,"sourceSpan":{"end":[86,50],"start":[86,16]}},"argument":{"annotation":{"meta":null,"sourceSpan":{"end":[86,50],"start":[86,20]}},"type":"Literal","value":{"literalType":"ArrayLiteral","value":[{"annotation":{"meta":null,"sourceSpan":{"end":[86,48],"start":[86,22]}},"type":"Literal","value":{"literalType":"StringLiteral","value":"lattice-color-hue-slider"}}]}},"type":"App"}]}},"type":"App"},"annotation":{"meta":null,"sourceSpan":{"end":[94,10],"start":[86,7]}},"argument":{"annotation":{"meta":null,"sourceSpan":{"end":[94,10],"start":[87,9]}},"type":"Literal","value":{"literalType":"ArrayLiteral","value":[{"abstraction":{"annotation":{"meta":{"metaType":"IsForeign"},"sourceSpan":{"end":[87,19],"start":[87,11]}},"type":"Var","value":{"identifier":"input","moduleName":["Halogen","HTML","Elements"]}},"annotation":{"meta":null,"sourceSpan":{"end":[93,14],"start":[87,11]}},"argument":{"annotation":{"meta":null,"sourceSpan":{"end":[93,14],"start":[88,13]}},"type":"Literal","value":{"literalType":"ArrayLiteral","value":[{"abstraction":{"annotation":{"meta":null,"sourceSpan":{"end":[0,0],"start":[0,0]}},"type":"Var","value":{"identifier":"type_","moduleName":["Lattice","UI","Components","ColorPicker"]}},"annotation":{"meta":null,"sourceSpan":{"end":[88,37],"start":[88,15]}},"argument":{"annotation":{"meta":{"constructorType":"SumType","identifiers":[],"metaType":"IsConstructor"},"sourceSpan":{"end":[88,37],"start":[88,24]}},"type":"Var","value":{"identifier":"InputRange","moduleName":["DOM","HTML","Indexed","InputType"]}},"type":"App"},{"abstraction":{"annotation":{"meta":{"metaType":"IsForeign"},"sourceSpan":{"end":[89,21],"start":[89,15]}},"type":"Var","value":{"identifier":"min","moduleName":["Halogen","HTML","Properties"]}},"annotation":{"meta":null,"sourceSpan":{"end":[89,25],"start":[89,15]}},"argument":{"annotation":{"meta":null,"sourceSpan":{"end":[89,25],"start":[89,22]}},"type":"Literal","value":{"literalType":"NumberLiteral","value":0}},"type":"App"},{"abstraction":{"annotation":{"meta":{"metaType":"IsForeign"},"sourceSpan":{"end":[90,21],"start":[90,15]}},"type":"Var","value":{"identifier":"max","moduleName":["Halogen","HTML","Properties"]}},"annotation":{"meta":null,"sourceSpan":{"end":[90,27],"start":[90,15]}},"argument":{"annotation":{"meta":null,"sourceSpan":{"end":[90,27],"start":[90,22]}},"type":"Literal","value":{"literalType":"NumberLiteral","value":360}},"type":"App"},{"abstraction":{"annotation":{"meta":null,"sourceSpan":{"end":[0,0],"start":[0,0]}},"type":"Var","value":{"identifier":"value","moduleName":["Lattice","UI","Components","ColorPicker"]}},"annotation":{"meta":null,"sourceSpan":{"end":[91,40],"start":[91,15]}},"argument":{"abstraction":{"annotation":{"meta":null,"sourceSpan":{"end":[0,0],"start":[0,0]}},"type":"Var","value":{"identifier":"show","moduleName":["Lattice","UI","Components","ColorPicker"]}},"annotation":{"meta":null,"sourceSpan":{"end":[91,39],"start":[91,25]}},"argument":{"annotation":{"meta":null,"sourceSpan":{"end":[91,39],"start":[91,30]}},"expression":{"annotation":{"meta":null,"sourceSpan":{"end":[91,35],"start":[91,30]}},"type":"Var","value":{"identifier":"state","sourcePos":[74,1]}},"fieldName":"hue","type":"Accessor"},"type":"App"},"type":"App"},{"abstraction":{"annotation":{"meta":{"metaType":"IsForeign"},"sourceSpan":{"end":[92,30],"start":[92,15]}},"type":"Var","value":{"identifier":"onValueInput","moduleName":["Halogen","HTML","Events"]}},"annotation":{"meta":null,"sourceSpan":{"end":[92,59],"start":[92,15]}},"argument":{"annotation":{"meta":null,"sourceSpan":{"end":[92,59],"start":[92,31]}},"argument":"v","body":{"abstraction":{"annotation":{"meta":{"constructorType":"SumType","identifiers":["value0"],"metaType":"IsConstructor"},"sourceSpan":{"end":[92,43],"start":[92,37]}},"type":"Var","value":{"identifier":"SetHue","moduleName":["Lattice","UI","Components","ColorPicker"]}},"annotation":{"meta":null,"sourceSpan":{"end":[92,59],"start":[92,37]}},"argument":{"abstraction":{"annotation":{"meta":null,"sourceSpan":{"end":[92,56],"start":[92,45]}},"type":"Var","value":{"identifier":"parseNumber","moduleName":["Lattice","UI","Components","ColorPicker"]}},"annotation":{"meta":null,"sourceSpan":{"end":[92,58],"start":[92,45]}},"argument":{"annotation":{"meta":null,"sourceSpan":{"end":[92,58],"start":[92,57]}},"type":"Var","value":{"identifier":"v","sourcePos":[92,32]}},"type":"App"},"type":"App"},"type":"Abs"},"type":"App"}]}},"type":"App"}]}},"type":"App"},{"abstraction":{"abstraction":{"annotation":{"meta":{"metaType":"IsForeign"},"sourceSpan":{"end":[95,13],"start":[95,7]}},"type":"Var","value":{"identifier":"div","moduleName":["Halogen","HTML","Elements"]}},"annotation":{"meta":null,"sourceSpan":{"end":[95,45],"start":[95,7]}},"argument":{"annotation":{"meta":null,"sourceSpan":{"end":[95,45],"start":[95,14]}},"type":"Literal","value":{"literalType":"ArrayLiteral","value":[{"abstraction":{"annotation":{"meta":{"metaType":"IsForeign"},"sourceSpan":{"end":[95,19],"start":[95,16]}},"type":"Var","value":{"identifier":"cls","moduleName":["Lattice","UI","Core"]}},"annotation":{"meta":null,"sourceSpan":{"end":[95,43],"start":[95,16]}},"argument":{"annotation":{"meta":null,"sourceSpan":{"end":[95,43],"start":[95,20]}},"type":"Literal","value":{"literalType":"ArrayLiteral","value":[{"annotation":{"meta":null,"sourceSpan":{"end":[95,41],"start":[95,22]}},"type":"Literal","value":{"literalType":"StringLiteral","value":"lattice-color-hex"}}]}},"type":"App"}]}},"type":"App"},"annotation":{"meta":null,"sourceSpan":{"end":[101,10],"start":[95,7]}},"argument":{"annotation":{"meta":null,"sourceSpan":{"end":[101,10],"start":[96,9]}},"type":"Literal","value":{"literalType":"ArrayLiteral","value":[{"abstraction":{"annotation":{"meta":{"metaType":"IsForeign"},"sourceSpan":{"end":[96,19],"start":[96,11]}},"type":"Var","value":{"identifier":"input","moduleName":["Halogen","HTML","Elements"]}},"annotation":{"meta":null,"sourceSpan":{"end":[100,14],"start":[96,11]}},"argument":{"annotation":{"meta":null,"sourceSpan":{"end":[100,14],"start":[97,13]}},"type":"Literal","value":{"literalType":"ArrayLiteral","value":[{"abstraction":{"annotation":{"meta":{"metaType":"IsForeign"},"sourceSpan":{"end":[97,18],"start":[97,15]}},"type":"Var","value":{"identifier":"cls","moduleName":["Lattice","UI","Core"]}},"annotation":{"meta":null,"sourceSpan":{"end":[97,38],"start":[97,15]}},"argument":{"annotation":{"meta":null,"sourceSpan":{"end":[97,38],"start":[97,19]}},"type":"Literal","value":{"literalType":"ArrayLiteral","value":[{"annotation":{"meta":null,"sourceSpan":{"end":[97,36],"start":[97,21]}},"type":"Literal","value":{"literalType":"StringLiteral","value":"lattice-input"}}]}},"type":"App"},{"abstraction":{"annotation":{"meta":null,"sourceSpan":{"end":[0,0],"start":[0,0]}},"type":"Var","value":{"identifier":"value","moduleName":["Lattice","UI","Components","ColorPicker"]}},"annotation":{"meta":null,"sourceSpan":{"end":[98,35],"start":[98,15]}},"argument":{"annotation":{"meta":null,"sourceSpan":{"end":[98,35],"start":[98,24]}},"expression":{"annotation":{"meta":null,"sourceSpan":{"end":[98,29],"start":[98,24]}},"type":"Var","value":{"identifier":"state","sourcePos":[74,1]}},"fieldName":"color","type":"Accessor"},"type":"App"},{"abstraction":{"annotation":{"meta":{"metaType":"IsForeign"},"sourceSpan":{"end":[99,30],"start":[99,15]}},"type":"Var","value":{"identifier":"onValueInput","moduleName":["Halogen","HTML","Events"]}},"annotation":{"meta":null,"sourceSpan":{"end":[99,37],"start":[99,15]}},"argument":{"annotation":{"meta":{"constructorType":"SumType","identifiers":["value0"],"metaType":"IsConstructor"},"sourceSpan":{"end":[99,37],"start":[99,31]}},"type":"Var","value":{"identifier":"SetHex","moduleName":["Lattice","UI","Components","ColorPicker"]}},"type":"App"}]}},"type":"App"}]}},"type":"App"}]}},"type":"App"},"type":"Abs"},"identifier":"renderPopover"},{"annotation":{"meta":null,"sourceSpan":{"end":[104,25],"start":[104,1]}},"bindType":"NonRec","expression":{"annotation":{"meta":null,"sourceSpan":{"end":[105,84],"start":[105,18]}},"type":"Literal","value":{"literalType":"StringLiteral","value":"display: flex; align-items: center; gap: var(--lattice-space-2);"}},"identifier":"containerStyle"},{"annotation":{"meta":null,"sourceSpan":{"end":[57,57],"start":[57,1]}},"bindType":"NonRec","expression":{"annotation":{"meta":null,"sourceSpan":{"end":[57,57],"start":[57,1]}},"argument":"state","body":{"abstraction":{"abstraction":{"annotation":{"meta":{"metaType":"IsForeign"},"sourceSpan":{"end":[59,9],"start":[59,3]}},"type":"Var","value":{"identifier":"div","moduleName":["Halogen","HTML","Elements"]}},"annotation":{"meta":null,"sourceSpan":{"end":[62,6],"start":[59,3]}},"argument":{"annotation":{"meta":null,"sourceSpan":{"end":[62,6],"start":[60,5]}},"type":"Literal","value":{"literalType":"ArrayLiteral","value":[{"abstraction":{"annotation":{"meta":{"metaType":"IsForeign"},"sourceSpan":{"end":[60,10],"start":[60,7]}},"type":"Var","value":{"identifier":"cls","moduleName":["Lattice","UI","Core"]}},"annotation":{"meta":null,"sourceSpan":{"end":[60,37],"start":[60,7]}},"argument":{"annotation":{"meta":null,"sourceSpan":{"end":[60,37],"start":[60,11]}},"type":"Literal","value":{"literalType":"ArrayLiteral","value":[{"annotation":{"meta":null,"sourceSpan":{"end":[60,35],"start":[60,13]}},"type":"Literal","value":{"literalType":"StringLiteral","value":"lattice-color-picker"}}]}},"type":"App"},{"abstraction":{"abstraction":{"annotation":{"meta":{"metaType":"IsForeign"},"sourceSpan":{"end":[61,14],"start":[61,7]}},"type":"Var","value":{"identifier":"attr","moduleName":["Halogen","HTML","Properties"]}},"annotation":{"meta":null,"sourceSpan":{"end":[61,36],"start":[61,7]}},"argument":{"abstraction":{"annotation":{"meta":{"metaType":"IsNewtype"},"sourceSpan":{"end":[61,27],"start":[61,16]}},"type":"Var","value":{"identifier":"AttrName","moduleName":["Web","HTML","Common"]}},"annotation":{"meta":null,"sourceSpan":{"end":[61,35],"start":[61,16]}},"argument":{"annotation":{"meta":null,"sourceSpan":{"end":[61,35],"start":[61,28]}},"type":"Literal","value":{"literalType":"StringLiteral","value":"style"}},"type":"App"},"type":"App"},"annotation":{"meta":null,"sourceSpan":{"end":[61,51],"start":[61,7]}},"argument":{"annotation":{"meta":null,"sourceSpan":{"end":[61,51],"start":[61,37]}},"type":"Var","value":{"identifier":"containerStyle","moduleName":["Lattice","UI","Components","ColorPicker"]}},"type":"App"}]}},"type":"App"},"annotation":{"meta":null,"sourceSpan":{"end":[71,6],"start":[59,3]}},"argument":{"annotation":{"meta":null,"sourceSpan":{"end":[71,6],"start":[63,5]}},"type":"Literal","value":{"literalType":"ArrayLiteral","value":[{"abstraction":{"abstraction":{"annotation":{"meta":{"metaType":"IsForeign"},"sourceSpan":{"end":[63,14],"start":[63,7]}},"type":"Var","value":{"identifier":"span","moduleName":["Halogen","HTML","Elements"]}},"annotation":{"meta":null,"sourceSpan":{"end":[63,48],"start":[63,7]}},"argument":{"annotation":{"meta":null,"sourceSpan":{"end":[63,48],"start":[63,15]}},"type":"Literal","value":{"literalType":"ArrayLiteral","value":[{"abstraction":{"annotation":{"meta":{"metaType":"IsForeign"},"sourceSpan":{"end":[63,20],"start":[63,17]}},"type":"Var","value":{"identifier":"cls","moduleName":["Lattice","UI","Core"]}},"annotation":{"meta":null,"sourceSpan":{"end":[63,46],"start":[63,17]}},"argument":{"annotation":{"meta":null,"sourceSpan":{"end":[63,46],"start":[63,21]}},"type":"Literal","value":{"literalType":"ArrayLiteral","value":[{"annotation":{"meta":null,"sourceSpan":{"end":[63,44],"start":[63,23]}},"type":"Literal","value":{"literalType":"StringLiteral","value":"lattice-color-label"}}]}},"type":"App"}]}},"type":"App"},"annotation":{"meta":null,"sourceSpan":{"end":[63,72],"start":[63,7]}},"argument":{"annotation":{"meta":null,"sourceSpan":{"end":[63,72],"start":[63,49]}},"type":"Literal","value":{"literalType":"ArrayLiteral","value":[{"abstraction":{"annotation":{"meta":{"metaType":"IsForeign"},"sourceSpan":{"end":[63,58],"start":[63,51]}},"type":"Var","value":{"identifier":"text","moduleName":["Halogen","HTML","Core"]}},"annotation":{"meta":null,"sourceSpan":{"end":[63,70],"start":[63,51]}},"argument":{"annotation":{"meta":null,"sourceSpan":{"end":[63,70],"start":[63,59]}},"expression":{"annotation":{"meta":null,"sourceSpan":{"end":[63,64],"start":[63,59]}},"type":"Var","value":{"identifier":"state","sourcePos":[58,1]}},"fieldName":"label","type":"Accessor"},"type":"App"}]}},"type":"App"},{"abstraction":{"abstraction":{"annotation":{"meta":{"metaType":"IsForeign"},"sourceSpan":{"end":[64,16],"start":[64,7]}},"type":"Var","value":{"identifier":"button","moduleName":["Halogen","HTML","Elements"]}},"annotation":{"meta":null,"sourceSpan":{"end":[68,10],"start":[64,7]}},"argument":{"annotation":{"meta":null,"sourceSpan":{"end":[68,10],"start":[65,9]}},"type":"Literal","value":{"literalType":"ArrayLiteral","value":[{"abstraction":{"annotation":{"meta":{"metaType":"IsForeign"},"sourceSpan":{"end":[65,14],"start":[65,11]}},"type":"Var","value":{"identifier":"cls","moduleName":["Lattice","UI","Core"]}},"annotation":{"meta":null,"sourceSpan":{"end":[65,41],"start":[65,11]}},"argument":{"annotation":{"meta":null,"sourceSpan":{"end":[65,41],"start":[65,15]}},"type":"Literal","value":{"literalType":"ArrayLiteral","value":[{"annotation":{"meta":null,"sourceSpan":{"end":[65,39],"start":[65,17]}},"type":"Literal","value":{"literalType":"StringLiteral","value":"lattice-color-swatch"}}]}},"type":"App"},{"abstraction":{"abstraction":{"annotation":{"meta":{"metaType":"IsForeign"},"sourceSpan":{"end":[66,18],"start":[66,11]}},"type":"Var","value":{"identifier":"attr","moduleName":["Halogen","HTML","Properties"]}},"annotation":{"meta":null,"sourceSpan":{"end":[66,40],"start":[66,11]}},"argument":{"abstraction":{"annotation":{"meta":{"metaType":"IsNewtype"},"sourceSpan":{"end":[66,31],"start":[66,20]}},"type":"Var","value":{"identifier":"AttrName","moduleName":["Web","HTML","Common"]}},"annotation":{"meta":null,"sourceSpan":{"end":[66,39],"start":[66,20]}},"argument":{"annotation":{"meta":null,"sourceSpan":{"end":[66,39],"start":[66,32]}},"type":"Literal","value":{"literalType":"StringLiteral","value":"style"}},"type":"App"},"type":"App"},"annotation":{"meta":null,"sourceSpan":{"end":[66,66],"start":[66,11]}},"argument":{"abstraction":{"annotation":{"meta":null,"sourceSpan":{"end":[66,53],"start":[66,42]}},"type":"Var","value":{"identifier":"swatchStyle","moduleName":["Lattice","UI","Components","ColorPicker"]}},"annotation":{"meta":null,"sourceSpan":{"end":[66,65],"start":[66,42]}},"argument":{"annotation":{"meta":null,"sourceSpan":{"end":[66,65],"start":[66,54]}},"expression":{"annotation":{"meta":null,"sourceSpan":{"end":[66,59],"start":[66,54]}},"type":"Var","value":{"identifier":"state","sourcePos":[58,1]}},"fieldName":"color","type":"Accessor"},"type":"App"},"type":"App"},{"abstraction":{"annotation":{"meta":{"metaType":"IsForeign"},"sourceSpan":{"end":[67,21],"start":[67,11]}},"type":"Var","value":{"identifier":"onClick","moduleName":["Halogen","HTML","Events"]}},"annotation":{"meta":null,"sourceSpan":{"end":[67,38],"start":[67,11]}},"argument":{"annotation":{"meta":null,"sourceSpan":{"end":[67,38],"start":[67,22]}},"argument":"v","body":{"annotation":{"meta":{"constructorType":"SumType","identifiers":[],"metaType":"IsConstructor"},"sourceSpan":{"end":[67,38],"start":[67,28]}},"type":"Var","value":{"identifier":"ToggleOpen","moduleName":["Lattice","UI","Components","ColorPicker"]}},"type":"Abs"},"type":"App"}]}},"type":"App"},"annotation":{"meta":null,"sourceSpan":{"end":[69,11],"start":[64,7]}},"argument":{"annotation":{"meta":null,"sourceSpan":{"end":[69,11],"start":[69,9]}},"type":"Literal","value":{"literalType":"ArrayLiteral","value":[]}},"type":"App"},{"annotation":{"meta":null,"sourceSpan":{"end":[70,63],"start":[70,7]}},"caseAlternatives":[{"binders":[{"annotation":{"meta":null,"sourceSpan":{"end":[70,63],"start":[70,7]}},"binderType":"LiteralBinder","literal":{"literalType":"BooleanLiteral","value":true}}],"expression":{"abstraction":{"annotation":{"meta":null,"sourceSpan":{"end":[70,41],"start":[70,28]}},"type":"Var","value":{"identifier":"renderPopover","moduleName":["Lattice","UI","Components","ColorPicker"]}},"annotation":{"meta":null,"sourceSpan":{"end":[70,47],"start":[70,28]}},"argument":{"annotation":{"meta":null,"sourceSpan":{"end":[70,47],"start":[70,42]}},"type":"Var","value":{"identifier":"state","sourcePos":[58,1]}},"type":"App"},"isGuarded":false},{"binders":[{"annotation":{"meta":null,"sourceSpan":{"end":[70,63],"start":[70,7]}},"binderType":"NullBinder"}],"expression":{"abstraction":{"annotation":{"meta":{"metaType":"IsForeign"},"sourceSpan":{"end":[70,60],"start":[70,53]}},"type":"Var","value":{"identifier":"text","moduleName":["Halogen","HTML","Core"]}},"annotation":{"meta":null,"sourceSpan":{"end":[70,63],"start":[70,53]}},"argument":{"annotation":{"meta":null,"sourceSpan":{"end":[70,63],"start":[70,61]}},"type":"Literal","value":{"literalType":"StringLiteral","value":""}},"type":"App"},"isGuarded":false}],"caseExpressions":[{"annotation":{"meta":null,"sourceSpan":{"end":[70,22],"start":[70,10]}},"expression":{"annotation":{"meta":null,"sourceSpan":{"end":[70,15],"start":[70,10]}},"type":"Var","value":{"identifier":"state","sourcePos":[58,1]}},"fieldName":"isOpen","type":"Accessor"}],"type":"Case"}]}},"type":"App"},"type":"Abs"},"identifier":"render"},{"annotation":{"meta":null,"sourceSpan":{"end":[36,68],"start":[36,1]}},"bindType":"NonRec","expression":{"annotation":{"meta":null,"sourceSpan":{"end":[36,68],"start":[36,1]}},"argument":"dictMonadAff","body":{"abstraction":{"annotation":{"meta":{"metaType":"IsForeign"},"sourceSpan":{"end":[37,26],"start":[37,13]}},"type":"Var","value":{"identifier":"mkComponent","moduleName":["Halogen","Component"]}},"annotation":{"meta":null,"sourceSpan":{"end":[45,4],"start":[37,13]}},"argument":{"annotation":{"meta":null,"sourceSpan":{"end":[45,4],"start":[38,3]}},"type":"Literal","value":{"literalType":"ObjectLiteral","value":[["initialState",{"annotation":{"meta":null,"sourceSpan":{"end":[38,17],"start":[38,5]}},"type":"Var","value":{"identifier":"initialState","moduleName":["Lattice","UI","Components","ColorPicker"]}}],["render",{"annotation":{"meta":null,"sourceSpan":{"end":[39,11],"start":[39,5]}},"type":"Var","value":{"identifier":"render","moduleName":["Lattice","UI","Components","ColorPicker"]}}],["eval",{"abstraction":{"annotation":{"meta":{"metaType":"IsForeign"},"sourceSpan":{"end":[40,19],"start":[40,11]}},"type":"Var","value":{"identifier":"mkEval","moduleName":["Halogen","Component"]}},"annotation":{"meta":null,"sourceSpan":{"end":[44,8],"start":[40,11]}},"argument":{"annotation":{"meta":null,"sourceSpan":{"end":[44,8],"start":[40,20]}},"binds":[{"annotation":{"meta":null,"sourceSpan":{"end":[45,4],"start":[37,1]}},"bindType":"NonRec","expression":{"annotation":{"meta":{"metaType":"IsForeign"},"sourceSpan":{"end":[40,33],"start":[40,20]}},"type":"Var","value":{"identifier":"defaultEval","moduleName":["Halogen","Component"]}},"identifier":"v"}],"expression":{"annotation":{"meta":null,"sourceSpan":{"end":[44,8],"start":[40,20]}},"copy":["handleQuery","finalize"],"expression":{"annotation":{"meta":null,"sourceSpan":{"end":[0,0],"start":[0,0]}},"type":"Var","value":{"identifier":"v","sourcePos":[37,1]}},"type":"ObjectUpdate","updates":[["handleAction",{"abstraction":{"annotation":{"meta":null,"sourceSpan":{"end":[41,36],"start":[41,24]}},"type":"Var","value":{"identifier":"handleAction","moduleName":["Lattice","UI","Components","ColorPicker"]}},"annotation":{"meta":{"metaType":"IsSyntheticApp"},"sourceSpan":{"end":[41,36],"start":[41,24]}},"argument":{"annotation":{"meta":null,"sourceSpan":{"end":[0,0],"start":[0,0]}},"type":"Var","value":{"identifier":"dictMonadAff","sourcePos":[0,0]}},"type":"App"}],["initialize",{"abstraction":{"annotation":{"meta":{"constructorType":"SumType","identifiers":["value0"],"metaType":"IsConstructor"},"sourceSpan":{"end":[42,26],"start":[42,22]}},"type":"Var","value":{"identifier":"Just","moduleName":["Data","Maybe"]}},"annotation":{"meta":null,"sourceSpan":{"end":[42,37],"start":[42,22]}},"argument":{"annotation":{"meta":{"constructorType":"SumType","identifiers":[],"metaType":"IsConstructor"},"sourceSpan":{"end":[42,37],"start":[42,27]}},"type":"Var","value":{"identifier":"Initialize","moduleName":["Lattice","UI","Components","ColorPicker"]}},"type":"App"}],["receive",{"abstraction":{"abstraction":{"annotation":{"meta":null,"sourceSpan":{"end":[0,0],"start":[0,0]}},"type":"Var","value":{"identifier":"compose","moduleName":["Lattice","UI","Components","ColorPicker"]}},"annotation":{"meta":null,"sourceSpan":{"end":[43,35],"start":[43,19]}},"argument":{"annotation":{"meta":{"constructorType":"SumType","identifiers":["value0"],"metaType":"IsConstructor"},"sourceSpan":{"end":[43,23],"start":[43,19]}},"type":"Var","value":{"identifier":"Just","moduleName":["Data","Maybe"]}},"type":"App"},"annotation":{"meta":null,"sourceSpan":{"end":[43,35],"start":[43,19]}},"argument":{"annotation":{"meta":{"constructorType":"SumType","identifiers":["value0"],"metaType":"IsConstructor"},"sourceSpan":{"end":[43,35],"start":[43,28]}},"type":"Var","value":{"identifier":"Receive","moduleName":["Lattice","UI","Components","ColorPicker"]}},"type":"App"}]]},"type":"Let"},"type":"App"}]]}},"type":"App"},"type":"Abs"},"identifier":"component"}],"exports":["ColorChanged","Initialize","Receive","ToggleOpen","SetHue","SetSaturation","SetLightness","SetHex","component","initialState","render","renderPopover","containerStyle","swatchStyle","popoverStyle","gradientStyle","parseNumber","handleAction","hslToHex"],"foreign":[],"imports":[{"annotation":{"meta":null,"sourceSpan":{"end":[155,30],"start":[2,1]}},"moduleName":["Control","Applicative"]},{"annotation":{"meta":null,"sourceSpan":{"end":[155,30],"start":[2,1]}},"moduleName":["Control","Bind"]},{"annotation":{"meta":null,"sourceSpan":{"end":[155,30],"start":[2,1]}},"moduleName":["Control","Monad","State","Class"]},{"annotation":{"meta":null,"sourceSpan":{"end":[155,30],"start":[2,1]}},"moduleName":["Control","Semigroupoid"]},{"annotation":{"meta":null,"sourceSpan":{"end":[155,30],"start":[2,1]}},"moduleName":["DOM","HTML","Indexed","InputType"]},{"annotation":{"meta":null,"sourceSpan":{"end":[155,30],"start":[2,1]}},"moduleName":["Data","HeytingAlgebra"]},{"annotation":{"meta":null,"sourceSpan":{"end":[155,30],"start":[2,1]}},"moduleName":["Data","Maybe"]},{"annotation":{"meta":null,"sourceSpan":{"end":[155,30],"start":[2,1]}},"moduleName":["Data","Semigroup"]},{"annotation":{"meta":null,"sourceSpan":{"end":[155,30],"start":[2,1]}},"moduleName":["Data","Show"]},{"annotation":{"meta":null,"sourceSpan":{"end":[155,30],"start":[2,1]}},"moduleName":["Data","Unit"]},{"annotation":{"meta":null,"sourceSpan":{"end":[6,41],"start":[6,1]}},"moduleName":["Effect","Aff","Class"]},{"annotation":{"meta":null,"sourceSpan":{"end":[7,20],"start":[7,1]}},"moduleName":["Halogen"]},{"annotation":{"meta":null,"sourceSpan":{"end":[155,30],"start":[2,1]}},"moduleName":["Halogen","Component"]},{"annotation":{"meta":null,"sourceSpan":{"end":[8,26],"start":[8,1]}},"moduleName":["Halogen","HTML"]},{"annotation":{"meta":null,"sourceSpan":{"end":[155,30],"start":[2,1]}},"moduleName":["Halogen","HTML","Core"]},{"annotation":{"meta":null,"sourceSpan":{"end":[155,30],"start":[2,1]}},"moduleName":["Halogen","HTML","Elements"]},{"annotation":{"meta":null,"sourceSpan":{"end":[155,30],"start":[2,1]}},"moduleName":["Halogen","HTML","Events"]},{"annotation":{"meta":null,"sourceSpan":{"end":[155,30],"start":[2,1]}},"moduleName":["Halogen","HTML","Properties"]},{"annotation":{"meta":null,"sourceSpan":{"end":[155,30],"start":[2,1]}},"moduleName":["Halogen","Query","HalogenM"]},{"annotation":{"meta":null,"sourceSpan":{"end":[155,30],"start":[2,1]}},"moduleName":["Lattice","UI","Components","ColorPicker"]},{"annotation":{"meta":null,"sourceSpan":{"end":[155,30],"start":[2,1]}},"moduleName":["Lattice","UI","Core"]},{"annotation":{"meta":null,"sourceSpan":{"end":[4,15],"start":[4,1]}},"moduleName":["Prelude"]},{"annotation":{"meta":null,"sourceSpan":{"end":[155,30],"start":[2,1]}},"moduleName":["Prim"]},{"annotation":{"meta":null,"sourceSpan":{"end":[155,30],"start":[2,1]}},"moduleName":["Web","HTML","Common"]}],"moduleName":["Lattice","UI","Components","ColorPicker"],"modulePath":"src/Lattice/UI/Components/ColorPicker.purs","reExports":{},"sourceSpan":{"end":[155,30],"start":[2,1]}}