{"comments":"Lattice.Services.Export.Types - Export service types\n\nPure types for video/image export pipelines.\nDepth maps, pose data, motion trajectories, video encoding.\n\nSource: ui/src/services/export/\n","declarations":[{"children":[],"comments":"Pipeline export options\n","info":{"arguments":[],"declType":"typeSynonym","type":{"annotation":[],"contents":[{"annotation":[],"contents":[["Prim"],"Record"],"tag":"TypeConstructor"},{"annotation":[],"contents":["width",{"annotation":[],"contents":[["Prim"],"Int"],"tag":"TypeConstructor"},{"annotation":[],"contents":["height",{"annotation":[],"contents":[["Prim"],"Int"],"tag":"TypeConstructor"},{"annotation":[],"contents":["frameRate",{"annotation":[],"contents":[["Prim"],"Int"],"tag":"TypeConstructor"},{"annotation":[],"contents":["startFrame",{"annotation":[],"contents":[["Prim"],"Int"],"tag":"TypeConstructor"},{"annotation":[],"contents":["endFrame",{"annotation":[],"contents":[["Prim"],"Int"],"tag":"TypeConstructor"},{"annotation":[],"contents":["format",{"annotation":[],"contents":[["Prim"],"String"],"tag":"TypeConstructor"},{"annotation":[],"contents":["quality",{"annotation":[],"contents":[["Prim"],"Number"],"tag":"TypeConstructor"},{"annotation":[],"contents":["includeAudio",{"annotation":[],"contents":[["Prim"],"Boolean"],"tag":"TypeConstructor"},{"annotation":[],"tag":"REmpty"}],"tag":"RCons"}],"tag":"RCons"}],"tag":"RCons"}],"tag":"RCons"}],"tag":"RCons"}],"tag":"RCons"}],"tag":"RCons"}],"tag":"RCons"}],"tag":"TypeApp"}},"kind":null,"sourceSpan":{"end":[91,4],"name":"src/Lattice/Services/Export/Types.purs","start":[82,1]},"title":"ExportPipelineOptions"},{"children":[],"comments":"A single rendered frame\n","info":{"arguments":[],"declType":"typeSynonym","type":{"annotation":[],"contents":[{"annotation":[],"contents":[["Prim"],"Record"],"tag":"TypeConstructor"},{"annotation":[],"contents":["frameNumber",{"annotation":[],"contents":[["Prim"],"Int"],"tag":"TypeConstructor"},{"annotation":[],"contents":["timestamp",{"annotation":[],"contents":[["Prim"],"Number"],"tag":"TypeConstructor"},{"annotation":[],"contents":["imageData",{"annotation":[],"contents":[["Prim"],"String"],"tag":"TypeConstructor"},{"annotation":[],"contents":["width",{"annotation":[],"contents":[["Prim"],"Int"],"tag":"TypeConstructor"},{"annotation":[],"contents":["height",{"annotation":[],"contents":[["Prim"],"Int"],"tag":"TypeConstructor"},{"annotation":[],"tag":"REmpty"}],"tag":"RCons"}],"tag":"RCons"}],"tag":"RCons"}],"tag":"RCons"}],"tag":"RCons"}],"tag":"TypeApp"}},"kind":null,"sourceSpan":{"end":[100,4],"name":"src/Lattice/Services/Export/Types.purs","start":[94,1]},"title":"RenderedFrame"},{"children":[],"comments":"Export progress\n","info":{"arguments":[],"declType":"typeSynonym","type":{"annotation":[],"contents":[{"annotation":[],"contents":[["Prim"],"Record"],"tag":"TypeConstructor"},{"annotation":[],"contents":["currentFrame",{"annotation":[],"contents":[["Prim"],"Int"],"tag":"TypeConstructor"},{"annotation":[],"contents":["totalFrames",{"annotation":[],"contents":[["Prim"],"Int"],"tag":"TypeConstructor"},{"annotation":[],"contents":["percentage",{"annotation":[],"contents":[["Prim"],"Number"],"tag":"TypeConstructor"},{"annotation":[],"contents":["stage",{"annotation":[],"contents":[["Prim"],"String"],"tag":"TypeConstructor"},{"annotation":[],"contents":["elapsedMs",{"annotation":[],"contents":[["Prim"],"Number"],"tag":"TypeConstructor"},{"annotation":[],"contents":["estimatedRemainingMs",{"annotation":[],"contents":[{"annotation":[],"contents":[["Data","Maybe"],"Maybe"],"tag":"TypeConstructor"},{"annotation":[],"contents":[["Prim"],"Number"],"tag":"TypeConstructor"}],"tag":"TypeApp"},{"annotation":[],"tag":"REmpty"}],"tag":"RCons"}],"tag":"RCons"}],"tag":"RCons"}],"tag":"RCons"}],"tag":"RCons"}],"tag":"RCons"}],"tag":"TypeApp"}},"kind":null,"sourceSpan":{"end":[110,4],"name":"src/Lattice/Services/Export/Types.purs","start":[103,1]},"title":"ExportProgress"},{"children":[{"comments":null,"info":{"arguments":[{"annotation":[],"contents":"a","tag":"TypeVar"}],"declType":"dataConstructor"},"sourceSpan":{"end":[114,18],"name":"src/Lattice/Services/Export/Types.purs","start":[114,3]},"title":"ExportSuccess"},{"comments":null,"info":{"arguments":[{"annotation":[],"contents":[["Prim"],"String"],"tag":"TypeConstructor"}],"declType":"dataConstructor"},"sourceSpan":{"end":[115,18],"name":"src/Lattice/Services/Export/Types.purs","start":[115,3]},"title":"ExportFailure"},{"comments":null,"info":{"arguments":[],"declType":"dataConstructor"},"sourceSpan":{"end":[116,20],"name":"src/Lattice/Services/Export/Types.purs","start":[116,3]},"title":"ExportCancelled"},{"comments":null,"info":{"declType":"instance","dependencies":[],"type":{"annotation":[],"contents":[{"annotation":[],"contents":[{"annotation":[],"contents":[["Data","Generic","Rep"],"Generic"],"tag":"TypeConstructor"},{"annotation":[],"contents":[{"annotation":[],"contents":[["Lattice","Services","Export","Types"],"ExportResult"],"tag":"TypeConstructor"},{"annotation":[],"contents":"a","tag":"TypeVar"}],"tag":"TypeApp"}],"tag":"TypeApp"},{"annotation":[],"contents":null,"tag":"TypeWildcard"}],"tag":"TypeApp"}},"sourceSpan":{"end":[118,43],"name":"src/Lattice/Services/Export/Types.purs","start":[118,1]},"title":"<anonymous>"},{"comments":null,"info":{"declType":"instance","dependencies":[{"constraintAnn":[],"constraintArgs":[{"annotation":[],"contents":"a","tag":"TypeVar"}],"constraintClass":[["Data","Show"],"Show"],"constraintData":null,"constraintKindArgs":[]}],"type":{"annotation":[],"contents":[{"annotation":[],"contents":[["Data","Show"],"Show"],"tag":"TypeConstructor"},{"annotation":[],"contents":[{"annotation":[],"contents":[["Lattice","Services","Export","Types"],"ExportResult"],"tag":"TypeConstructor"},{"annotation":[],"contents":"a","tag":"TypeVar"}],"tag":"TypeApp"}],"tag":"TypeApp"}},"sourceSpan":{"end":[119,66],"name":"src/Lattice/Services/Export/Types.purs","start":[119,1]},"title":"<anonymous>"},{"comments":null,"info":{"declType":"instance","dependencies":[{"constraintAnn":[],"constraintArgs":[{"annotation":[],"contents":"a","tag":"TypeVar"}],"constraintClass":[["Data","Eq"],"Eq"],"constraintData":null,"constraintKindArgs":[]}],"type":{"annotation":[],"contents":[{"annotation":[],"contents":[["Data","Eq"],"Eq"],"tag":"TypeConstructor"},{"annotation":[],"contents":[{"annotation":[],"contents":[["Lattice","Services","Export","Types"],"ExportResult"],"tag":"TypeConstructor"},{"annotation":[],"contents":"a","tag":"TypeVar"}],"tag":"TypeApp"}],"tag":"TypeApp"}},"sourceSpan":{"end":[120,58],"name":"src/Lattice/Services/Export/Types.purs","start":[120,1]},"title":"<anonymous>"}],"comments":"Export result\n","info":{"dataDeclType":"data","declType":"data","roles":["Representational"],"typeArguments":[["a",null]]},"kind":null,"sourceSpan":{"end":[116,20],"name":"src/Lattice/Services/Export/Types.purs","start":[113,1]},"title":"ExportResult"},{"children":[{"comments":null,"info":{"arguments":[],"declType":"dataConstructor"},"sourceSpan":{"end":[128,21],"name":"src/Lattice/Services/Export/Types.purs","start":[128,3]},"title":"DepthGrayscale16"},{"comments":null,"info":{"arguments":[],"declType":"dataConstructor"},"sourceSpan":{"end":[129,20],"name":"src/Lattice/Services/Export/Types.purs","start":[129,3]},"title":"DepthGrayscale8"},{"comments":null,"info":{"arguments":[],"declType":"dataConstructor"},"sourceSpan":{"end":[130,20],"name":"src/Lattice/Services/Export/Types.purs","start":[130,3]},"title":"DepthNormalized"},{"comments":null,"info":{"arguments":[],"declType":"dataConstructor"},"sourceSpan":{"end":[131,13],"name":"src/Lattice/Services/Export/Types.purs","start":[131,3]},"title":"DepthRaw"},{"comments":null,"info":{"declType":"instance","dependencies":[],"type":{"annotation":[],"contents":[{"annotation":[],"contents":[{"annotation":[],"contents":[["Data","Generic","Rep"],"Generic"],"tag":"TypeConstructor"},{"annotation":[],"contents":[["Lattice","Services","Export","Types"],"DepthFormat"],"tag":"TypeConstructor"}],"tag":"TypeApp"},{"annotation":[],"contents":null,"tag":"TypeWildcard"}],"tag":"TypeApp"}},"sourceSpan":{"end":[133,38],"name":"src/Lattice/Services/Export/Types.purs","start":[133,1]},"title":"<anonymous>"},{"comments":null,"info":{"declType":"instance","dependencies":[],"type":{"annotation":[],"contents":[{"annotation":[],"contents":[["Data","Show"],"Show"],"tag":"TypeConstructor"},{"annotation":[],"contents":[["Lattice","Services","Export","Types"],"DepthFormat"],"tag":"TypeConstructor"}],"tag":"TypeApp"}},"sourceSpan":{"end":[134,51],"name":"src/Lattice/Services/Export/Types.purs","start":[134,1]},"title":"<anonymous>"},{"comments":null,"info":{"declType":"instance","dependencies":[],"type":{"annotation":[],"contents":[{"annotation":[],"contents":[["Data","Eq"],"Eq"],"tag":"TypeConstructor"},{"annotation":[],"contents":[["Lattice","Services","Export","Types"],"DepthFormat"],"tag":"TypeConstructor"}],"tag":"TypeApp"}},"sourceSpan":{"end":[135,45],"name":"src/Lattice/Services/Export/Types.purs","start":[135,1]},"title":"<anonymous>"}],"comments":"Depth output format\n","info":{"dataDeclType":"data","declType":"data","roles":[],"typeArguments":[]},"kind":null,"sourceSpan":{"end":[131,13],"name":"src/Lattice/Services/Export/Types.purs","start":[127,1]},"title":"DepthFormat"},{"children":[],"comments":"Options for depth generation\n","info":{"arguments":[],"declType":"typeSynonym","type":{"annotation":[],"contents":[{"annotation":[],"contents":[["Prim"],"Record"],"tag":"TypeConstructor"},{"annotation":[],"contents":["model",{"annotation":[],"contents":[["Prim"],"String"],"tag":"TypeConstructor"},{"annotation":[],"contents":["precision",{"annotation":[],"contents":[["Prim"],"String"],"tag":"TypeConstructor"},{"annotation":[],"contents":["normalize",{"annotation":[],"contents":[["Prim"],"Boolean"],"tag":"TypeConstructor"},{"annotation":[],"contents":["invert",{"annotation":[],"contents":[["Prim"],"Boolean"],"tag":"TypeConstructor"},{"annotation":[],"contents":["colormap",{"annotation":[],"contents":[{"annotation":[],"contents":[["Data","Maybe"],"Maybe"],"tag":"TypeConstructor"},{"annotation":[],"contents":[["Prim"],"String"],"tag":"TypeConstructor"}],"tag":"TypeApp"},{"annotation":[],"tag":"REmpty"}],"tag":"RCons"}],"tag":"RCons"}],"tag":"RCons"}],"tag":"RCons"}],"tag":"RCons"}],"tag":"TypeApp"}},"kind":null,"sourceSpan":{"end":[144,4],"name":"src/Lattice/Services/Export/Types.purs","start":[138,1]},"title":"DepthGenerationOptions"},{"children":[],"comments":"Result of depth generation\n","info":{"arguments":[],"declType":"typeSynonym","type":{"annotation":[],"contents":[{"annotation":[],"contents":[["Prim"],"Record"],"tag":"TypeConstructor"},{"annotation":[],"contents":["success",{"annotation":[],"contents":[["Prim"],"Boolean"],"tag":"TypeConstructor"},{"annotation":[],"contents":["depthMap",{"annotation":[],"contents":[{"annotation":[],"contents":[["Data","Maybe"],"Maybe"],"tag":"TypeConstructor"},{"annotation":[],"contents":[["Prim"],"String"],"tag":"TypeConstructor"}],"tag":"TypeApp"},{"annotation":[],"contents":["width",{"annotation":[],"contents":[["Prim"],"Int"],"tag":"TypeConstructor"},{"annotation":[],"contents":["height",{"annotation":[],"contents":[["Prim"],"Int"],"tag":"TypeConstructor"},{"annotation":[],"contents":["minDepth",{"annotation":[],"contents":[["Prim"],"Number"],"tag":"TypeConstructor"},{"annotation":[],"contents":["maxDepth",{"annotation":[],"contents":[["Prim"],"Number"],"tag":"TypeConstructor"},{"annotation":[],"contents":["error",{"annotation":[],"contents":[{"annotation":[],"contents":[["Data","Maybe"],"Maybe"],"tag":"TypeConstructor"},{"annotation":[],"contents":[["Prim"],"String"],"tag":"TypeConstructor"}],"tag":"TypeApp"},{"annotation":[],"tag":"REmpty"}],"tag":"RCons"}],"tag":"RCons"}],"tag":"RCons"}],"tag":"RCons"}],"tag":"RCons"}],"tag":"RCons"}],"tag":"RCons"}],"tag":"TypeApp"}},"kind":null,"sourceSpan":{"end":[155,4],"name":"src/Lattice/Services/Export/Types.purs","start":[147,1]},"title":"DepthGenerationResult"},{"children":[],"comments":"Depth sequence metadata\n","info":{"arguments":[],"declType":"typeSynonym","type":{"annotation":[],"contents":[{"annotation":[],"contents":[["Prim"],"Record"],"tag":"TypeConstructor"},{"annotation":[],"contents":["frameCount",{"annotation":[],"contents":[["Prim"],"Int"],"tag":"TypeConstructor"},{"annotation":[],"contents":["width",{"annotation":[],"contents":[["Prim"],"Int"],"tag":"TypeConstructor"},{"annotation":[],"contents":["height",{"annotation":[],"contents":[["Prim"],"Int"],"tag":"TypeConstructor"},{"annotation":[],"contents":["minDepth",{"annotation":[],"contents":[["Prim"],"Number"],"tag":"TypeConstructor"},{"annotation":[],"contents":["maxDepth",{"annotation":[],"contents":[["Prim"],"Number"],"tag":"TypeConstructor"},{"annotation":[],"contents":["format",{"annotation":[],"contents":[["Lattice","Services","Export","Types"],"DepthFormat"],"tag":"TypeConstructor"},{"annotation":[],"tag":"REmpty"}],"tag":"RCons"}],"tag":"RCons"}],"tag":"RCons"}],"tag":"RCons"}],"tag":"RCons"}],"tag":"RCons"}],"tag":"TypeApp"}},"kind":null,"sourceSpan":{"end":[165,4],"name":"src/Lattice/Services/Export/Types.purs","start":[158,1]},"title":"DepthMetadata"},{"children":[],"comments":"Options for normal map generation\n","info":{"arguments":[],"declType":"typeSynonym","type":{"annotation":[],"contents":[{"annotation":[],"contents":[["Prim"],"Record"],"tag":"TypeConstructor"},{"annotation":[],"contents":["model",{"annotation":[],"contents":[["Prim"],"String"],"tag":"TypeConstructor"},{"annotation":[],"contents":["precision",{"annotation":[],"contents":[["Prim"],"String"],"tag":"TypeConstructor"},{"annotation":[],"contents":["normalize",{"annotation":[],"contents":[["Prim"],"Boolean"],"tag":"TypeConstructor"},{"annotation":[],"tag":"REmpty"}],"tag":"RCons"}],"tag":"RCons"}],"tag":"RCons"}],"tag":"TypeApp"}},"kind":null,"sourceSpan":{"end":[176,4],"name":"src/Lattice/Services/Export/Types.purs","start":[172,1]},"title":"NormalGenerationOptions"},{"children":[],"comments":"Result of normal generation\n","info":{"arguments":[],"declType":"typeSynonym","type":{"annotation":[],"contents":[{"annotation":[],"contents":[["Prim"],"Record"],"tag":"TypeConstructor"},{"annotation":[],"contents":["success",{"annotation":[],"contents":[["Prim"],"Boolean"],"tag":"TypeConstructor"},{"annotation":[],"contents":["normalMap",{"annotation":[],"contents":[{"annotation":[],"contents":[["Data","Maybe"],"Maybe"],"tag":"TypeConstructor"},{"annotation":[],"contents":[["Prim"],"String"],"tag":"TypeConstructor"}],"tag":"TypeApp"},{"annotation":[],"contents":["width",{"annotation":[],"contents":[["Prim"],"Int"],"tag":"TypeConstructor"},{"annotation":[],"contents":["height",{"annotation":[],"contents":[["Prim"],"Int"],"tag":"TypeConstructor"},{"annotation":[],"contents":["error",{"annotation":[],"contents":[{"annotation":[],"contents":[["Data","Maybe"],"Maybe"],"tag":"TypeConstructor"},{"annotation":[],"contents":[["Prim"],"String"],"tag":"TypeConstructor"}],"tag":"TypeApp"},{"annotation":[],"tag":"REmpty"}],"tag":"RCons"}],"tag":"RCons"}],"tag":"RCons"}],"tag":"RCons"}],"tag":"RCons"}],"tag":"TypeApp"}},"kind":null,"sourceSpan":{"end":[185,4],"name":"src/Lattice/Services/Export/Types.purs","start":[179,1]},"title":"NormalGenerationResult"},{"children":[],"comments":"Pose export configuration\n","info":{"arguments":[],"declType":"typeSynonym","type":{"annotation":[],"contents":[{"annotation":[],"contents":[["Prim"],"Record"],"tag":"TypeConstructor"},{"annotation":[],"contents":["includeHands",{"annotation":[],"contents":[["Prim"],"Boolean"],"tag":"TypeConstructor"},{"annotation":[],"contents":["includeFace",{"annotation":[],"contents":[["Prim"],"Boolean"],"tag":"TypeConstructor"},{"annotation":[],"contents":["format",{"annotation":[],"contents":[["Prim"],"String"],"tag":"TypeConstructor"},{"annotation":[],"contents":["resolution",{"annotation":[],"contents":[{"annotation":[],"contents":[["Prim"],"Record"],"tag":"TypeConstructor"},{"annotation":[],"contents":["width",{"annotation":[],"contents":[["Prim"],"Int"],"tag":"TypeConstructor"},{"annotation":[],"contents":["height",{"annotation":[],"contents":[["Prim"],"Int"],"tag":"TypeConstructor"},{"annotation":[],"tag":"REmpty"}],"tag":"RCons"}],"tag":"RCons"}],"tag":"TypeApp"},{"annotation":[],"contents":["confidence",{"annotation":[],"contents":[["Prim"],"Number"],"tag":"TypeConstructor"},{"annotation":[],"tag":"REmpty"}],"tag":"RCons"}],"tag":"RCons"}],"tag":"RCons"}],"tag":"RCons"}],"tag":"RCons"}],"tag":"TypeApp"}},"kind":null,"sourceSpan":{"end":[198,4],"name":"src/Lattice/Services/Export/Types.purs","start":[192,1]},"title":"PoseExportConfig"},{"children":[],"comments":"Pose export result\n","info":{"arguments":[],"declType":"typeSynonym","type":{"annotation":[],"contents":[{"annotation":[],"contents":[["Prim"],"Record"],"tag":"TypeConstructor"},{"annotation":[],"contents":["success",{"annotation":[],"contents":[["Prim"],"Boolean"],"tag":"TypeConstructor"},{"annotation":[],"contents":["frames",{"annotation":[],"contents":[{"annotation":[],"contents":[["Prim"],"Array"],"tag":"TypeConstructor"},{"annotation":[],"contents":[["Lattice","Services","Export","Types"],"PoseFrame"],"tag":"TypeConstructor"}],"tag":"TypeApp"},{"annotation":[],"contents":["format",{"annotation":[],"contents":[["Prim"],"String"],"tag":"TypeConstructor"},{"annotation":[],"contents":["error",{"annotation":[],"contents":[{"annotation":[],"contents":[["Data","Maybe"],"Maybe"],"tag":"TypeConstructor"},{"annotation":[],"contents":[["Prim"],"String"],"tag":"TypeConstructor"}],"tag":"TypeApp"},{"annotation":[],"tag":"REmpty"}],"tag":"RCons"}],"tag":"RCons"}],"tag":"RCons"}],"tag":"RCons"}],"tag":"TypeApp"}},"kind":null,"sourceSpan":{"end":[206,4],"name":"src/Lattice/Services/Export/Types.purs","start":[201,1]},"title":"PoseExportResult"},{"children":[],"comments":"A single pose frame\n","info":{"arguments":[],"declType":"typeSynonym","type":{"annotation":[],"contents":[{"annotation":[],"contents":[["Prim"],"Record"],"tag":"TypeConstructor"},{"annotation":[],"contents":["frameNumber",{"annotation":[],"contents":[["Prim"],"Int"],"tag":"TypeConstructor"},{"annotation":[],"contents":["people",{"annotation":[],"contents":[{"annotation":[],"contents":[["Prim"],"Array"],"tag":"TypeConstructor"},{"annotation":[],"contents":[["Lattice","Services","Export","Types"],"OpenPoseJSON"],"tag":"TypeConstructor"}],"tag":"TypeApp"},{"annotation":[],"contents":["canvas",{"annotation":[],"contents":[{"annotation":[],"contents":[["Data","Maybe"],"Maybe"],"tag":"TypeConstructor"},{"annotation":[],"contents":[["Prim"],"String"],"tag":"TypeConstructor"}],"tag":"TypeApp"},{"annotation":[],"tag":"REmpty"}],"tag":"RCons"}],"tag":"RCons"}],"tag":"RCons"}],"tag":"TypeApp"}},"kind":null,"sourceSpan":{"end":[213,4],"name":"src/Lattice/Services/Export/Types.purs","start":[209,1]},"title":"PoseFrame"},{"children":[],"comments":"Pose sequence\n","info":{"arguments":[],"declType":"typeSynonym","type":{"annotation":[],"contents":[{"annotation":[],"contents":[["Prim"],"Record"],"tag":"TypeConstructor"},{"annotation":[],"contents":["frames",{"annotation":[],"contents":[{"annotation":[],"contents":[["Prim"],"Array"],"tag":"TypeConstructor"},{"annotation":[],"contents":[["Lattice","Services","Export","Types"],"PoseFrame"],"tag":"TypeConstructor"}],"tag":"TypeApp"},{"annotation":[],"contents":["width",{"annotation":[],"contents":[["Prim"],"Int"],"tag":"TypeConstructor"},{"annotation":[],"contents":["height",{"annotation":[],"contents":[["Prim"],"Int"],"tag":"TypeConstructor"},{"annotation":[],"contents":["frameRate",{"annotation":[],"contents":[["Prim"],"Int"],"tag":"TypeConstructor"},{"annotation":[],"tag":"REmpty"}],"tag":"RCons"}],"tag":"RCons"}],"tag":"RCons"}],"tag":"RCons"}],"tag":"TypeApp"}},"kind":null,"sourceSpan":{"end":[221,4],"name":"src/Lattice/Services/Export/Types.purs","start":[216,1]},"title":"PoseSequence"},{"children":[],"comments":"OpenPose JSON format\n","info":{"arguments":[],"declType":"typeSynonym","type":{"annotation":[],"contents":[{"annotation":[],"contents":[["Prim"],"Record"],"tag":"TypeConstructor"},{"annotation":[],"contents":["pose_keypoints_2d",{"annotation":[],"contents":[{"annotation":[],"contents":[["Prim"],"Array"],"tag":"TypeConstructor"},{"annotation":[],"contents":[["Prim"],"Number"],"tag":"TypeConstructor"}],"tag":"TypeApp"},{"annotation":[],"contents":["face_keypoints_2d",{"annotation":[],"contents":[{"annotation":[],"contents":[["Data","Maybe"],"Maybe"],"tag":"TypeConstructor"},{"annotation":[],"contents":{"annotation":[],"contents":[{"annotation":[],"contents":[["Prim"],"Array"],"tag":"TypeConstructor"},{"annotation":[],"contents":[["Prim"],"Number"],"tag":"TypeConstructor"}],"tag":"TypeApp"},"tag":"ParensInType"}],"tag":"TypeApp"},{"annotation":[],"contents":["hand_left_keypoints_2d",{"annotation":[],"contents":[{"annotation":[],"contents":[["Data","Maybe"],"Maybe"],"tag":"TypeConstructor"},{"annotation":[],"contents":{"annotation":[],"contents":[{"annotation":[],"contents":[["Prim"],"Array"],"tag":"TypeConstructor"},{"annotation":[],"contents":[["Prim"],"Number"],"tag":"TypeConstructor"}],"tag":"TypeApp"},"tag":"ParensInType"}],"tag":"TypeApp"},{"annotation":[],"contents":["hand_right_keypoints_2d",{"annotation":[],"contents":[{"annotation":[],"contents":[["Data","Maybe"],"Maybe"],"tag":"TypeConstructor"},{"annotation":[],"contents":{"annotation":[],"contents":[{"annotation":[],"contents":[["Prim"],"Array"],"tag":"TypeConstructor"},{"annotation":[],"contents":[["Prim"],"Number"],"tag":"TypeConstructor"}],"tag":"TypeApp"},"tag":"ParensInType"}],"tag":"TypeApp"},{"annotation":[],"tag":"REmpty"}],"tag":"RCons"}],"tag":"RCons"}],"tag":"RCons"}],"tag":"RCons"}],"tag":"TypeApp"}},"kind":null,"sourceSpan":{"end":[229,4],"name":"src/Lattice/Services/Export/Types.purs","start":[224,1]},"title":"OpenPoseJSON"},{"children":[],"comments":"A single track point\n","info":{"arguments":[],"declType":"typeSynonym","type":{"annotation":[],"contents":[{"annotation":[],"contents":[["Prim"],"Record"],"tag":"TypeConstructor"},{"annotation":[],"contents":["x",{"annotation":[],"contents":[["Prim"],"Number"],"tag":"TypeConstructor"},{"annotation":[],"contents":["y",{"annotation":[],"contents":[["Prim"],"Number"],"tag":"TypeConstructor"},{"annotation":[],"tag":"REmpty"}],"tag":"RCons"}],"tag":"RCons"}],"tag":"TypeApp"}},"kind":null,"sourceSpan":{"end":[236,47],"name":"src/Lattice/Services/Export/Types.purs","start":[236,1]},"title":"TrackPoint"},{"children":[],"comments":"A point trajectory over time\n","info":{"arguments":[],"declType":"typeSynonym","type":{"annotation":[],"contents":[{"annotation":[],"contents":[["Prim"],"Record"],"tag":"TypeConstructor"},{"annotation":[],"contents":["points",{"annotation":[],"contents":[{"annotation":[],"contents":[["Prim"],"Array"],"tag":"TypeConstructor"},{"annotation":[],"contents":[["Lattice","Services","Export","Types"],"TrackPoint"],"tag":"TypeConstructor"}],"tag":"TypeApp"},{"annotation":[],"contents":["startFrame",{"annotation":[],"contents":[["Prim"],"Int"],"tag":"TypeConstructor"},{"annotation":[],"contents":["endFrame",{"annotation":[],"contents":[["Prim"],"Int"],"tag":"TypeConstructor"},{"annotation":[],"tag":"REmpty"}],"tag":"RCons"}],"tag":"RCons"}],"tag":"RCons"}],"tag":"TypeApp"}},"kind":null,"sourceSpan":{"end":[243,4],"name":"src/Lattice/Services/Export/Types.purs","start":[239,1]},"title":"PointTrajectory"},{"children":[],"comments":"Wan-Move trajectory format\n","info":{"arguments":[],"declType":"typeSynonym","type":{"annotation":[],"contents":[{"annotation":[],"contents":[["Prim"],"Record"],"tag":"TypeConstructor"},{"annotation":[],"contents":["tracks",{"annotation":[],"contents":[{"annotation":[],"contents":[["Prim"],"Array"],"tag":"TypeConstructor"},{"annotation":[],"contents":{"annotation":[],"contents":[{"annotation":[],"contents":[["Prim"],"Array"],"tag":"TypeConstructor"},{"annotation":[],"contents":{"annotation":[],"contents":[{"annotation":[],"contents":[["Prim"],"Array"],"tag":"TypeConstructor"},{"annotation":[],"contents":[["Prim"],"Number"],"tag":"TypeConstructor"}],"tag":"TypeApp"},"tag":"ParensInType"}],"tag":"TypeApp"},"tag":"ParensInType"}],"tag":"TypeApp"},{"annotation":[],"contents":["width",{"annotation":[],"contents":[["Prim"],"Int"],"tag":"TypeConstructor"},{"annotation":[],"contents":["height",{"annotation":[],"contents":[["Prim"],"Int"],"tag":"TypeConstructor"},{"annotation":[],"contents":["frameCount",{"annotation":[],"contents":[["Prim"],"Int"],"tag":"TypeConstructor"},{"annotation":[],"tag":"REmpty"}],"tag":"RCons"}],"tag":"RCons"}],"tag":"RCons"}],"tag":"RCons"}],"tag":"TypeApp"}},"kind":null,"sourceSpan":{"end":[251,4],"name":"src/Lattice/Services/Export/Types.purs","start":[246,1]},"title":"WanMoveTrajectory"},{"children":[],"comments":"Wan-Move trajectory export\n","info":{"arguments":[],"declType":"typeSynonym","type":{"annotation":[],"contents":[{"annotation":[],"contents":[["Prim"],"Record"],"tag":"TypeConstructor"},{"annotation":[],"contents":["tracks",{"annotation":[],"contents":[{"annotation":[],"contents":[["Prim"],"Array"],"tag":"TypeConstructor"},{"annotation":[],"contents":{"annotation":[],"contents":[{"annotation":[],"contents":[["Prim"],"Array"],"tag":"TypeConstructor"},{"annotation":[],"contents":[["Lattice","Services","Export","Types"],"TrackPoint"],"tag":"TypeConstructor"}],"tag":"TypeApp"},"tag":"ParensInType"}],"tag":"TypeApp"},{"annotation":[],"contents":["visibility",{"annotation":[],"contents":[{"annotation":[],"contents":[["Data","Maybe"],"Maybe"],"tag":"TypeConstructor"},{"annotation":[],"contents":{"annotation":[],"contents":[{"annotation":[],"contents":[["Prim"],"Array"],"tag":"TypeConstructor"},{"annotation":[],"contents":{"annotation":[],"contents":[{"annotation":[],"contents":[["Prim"],"Array"],"tag":"TypeConstructor"},{"annotation":[],"contents":[["Prim"],"Boolean"],"tag":"TypeConstructor"}],"tag":"TypeApp"},"tag":"ParensInType"}],"tag":"TypeApp"},"tag":"ParensInType"}],"tag":"TypeApp"},{"annotation":[],"contents":["metadata",{"annotation":[],"contents":[{"annotation":[],"contents":[["Prim"],"Record"],"tag":"TypeConstructor"},{"annotation":[],"contents":["width",{"annotation":[],"contents":[["Prim"],"Int"],"tag":"TypeConstructor"},{"annotation":[],"contents":["height",{"annotation":[],"contents":[["Prim"],"Int"],"tag":"TypeConstructor"},{"annotation":[],"contents":["frames",{"annotation":[],"contents":[["Prim"],"Int"],"tag":"TypeConstructor"},{"annotation":[],"tag":"REmpty"}],"tag":"RCons"}],"tag":"RCons"}],"tag":"RCons"}],"tag":"TypeApp"},{"annotation":[],"tag":"REmpty"}],"tag":"RCons"}],"tag":"RCons"}],"tag":"RCons"}],"tag":"TypeApp"}},"kind":null,"sourceSpan":{"end":[258,4],"name":"src/Lattice/Services/Export/Types.purs","start":[254,1]},"title":"WanMoveTrajectoryExport"},{"children":[],"comments":"ATI export result\n","info":{"arguments":[],"declType":"typeSynonym","type":{"annotation":[],"contents":[{"annotation":[],"contents":[["Prim"],"Record"],"tag":"TypeConstructor"},{"annotation":[],"contents":["trajectories",{"annotation":[],"contents":[{"annotation":[],"contents":[["Prim"],"Array"],"tag":"TypeConstructor"},{"annotation":[],"contents":{"annotation":[],"contents":[{"annotation":[],"contents":[["Prim"],"Array"],"tag":"TypeConstructor"},{"annotation":[],"contents":[["Lattice","Services","Export","Types"],"ATITrackPoint"],"tag":"TypeConstructor"}],"tag":"TypeApp"},"tag":"ParensInType"}],"tag":"TypeApp"},{"annotation":[],"contents":["frameCount",{"annotation":[],"contents":[["Prim"],"Int"],"tag":"TypeConstructor"},{"annotation":[],"contents":["normalized",{"annotation":[],"contents":[["Prim"],"Boolean"],"tag":"TypeConstructor"},{"annotation":[],"tag":"REmpty"}],"tag":"RCons"}],"tag":"RCons"}],"tag":"RCons"}],"tag":"TypeApp"}},"kind":null,"sourceSpan":{"end":[265,4],"name":"src/Lattice/Services/Export/Types.purs","start":[261,1]},"title":"ATIExportResult"},{"children":[],"comments":"ATI track point\n","info":{"arguments":[],"declType":"typeSynonym","type":{"annotation":[],"contents":[{"annotation":[],"contents":[["Prim"],"Record"],"tag":"TypeConstructor"},{"annotation":[],"contents":["x",{"annotation":[],"contents":[["Prim"],"Number"],"tag":"TypeConstructor"},{"annotation":[],"contents":["y",{"annotation":[],"contents":[["Prim"],"Number"],"tag":"TypeConstructor"},{"annotation":[],"contents":["visible",{"annotation":[],"contents":[["Prim"],"Boolean"],"tag":"TypeConstructor"},{"annotation":[],"tag":"REmpty"}],"tag":"RCons"}],"tag":"RCons"}],"tag":"RCons"}],"tag":"TypeApp"}},"kind":null,"sourceSpan":{"end":[272,4],"name":"src/Lattice/Services/Export/Types.purs","start":[268,1]},"title":"ATITrackPoint"},{"children":[],"comments":"Configuration for generative flow\n","info":{"arguments":[],"declType":"typeSynonym","type":{"annotation":[],"contents":[{"annotation":[],"contents":[["Prim"],"Record"],"tag":"TypeConstructor"},{"annotation":[],"contents":["flowType",{"annotation":[],"contents":[["Prim"],"String"],"tag":"TypeConstructor"},{"annotation":[],"contents":["pointCount",{"annotation":[],"contents":[["Prim"],"Int"],"tag":"TypeConstructor"},{"annotation":[],"contents":["frameCount",{"annotation":[],"contents":[["Prim"],"Int"],"tag":"TypeConstructor"},{"annotation":[],"contents":["width",{"annotation":[],"contents":[["Prim"],"Int"],"tag":"TypeConstructor"},{"annotation":[],"contents":["height",{"annotation":[],"contents":[["Prim"],"Int"],"tag":"TypeConstructor"},{"annotation":[],"contents":["seed",{"annotation":[],"contents":[{"annotation":[],"contents":[["Data","Maybe"],"Maybe"],"tag":"TypeConstructor"},{"annotation":[],"contents":[["Prim"],"Int"],"tag":"TypeConstructor"}],"tag":"TypeApp"},{"annotation":[],"tag":"REmpty"}],"tag":"RCons"}],"tag":"RCons"}],"tag":"RCons"}],"tag":"RCons"}],"tag":"RCons"}],"tag":"RCons"}],"tag":"TypeApp"}},"kind":null,"sourceSpan":{"end":[286,4],"name":"src/Lattice/Services/Export/Types.purs","start":[279,1]},"title":"GenerativeFlowConfig"},{"children":[],"comments":"Parameters for flow generation\n","info":{"arguments":[],"declType":"typeSynonym","type":{"annotation":[],"contents":[{"annotation":[],"contents":[["Prim"],"Record"],"tag":"TypeConstructor"},{"annotation":[],"contents":["speed",{"annotation":[],"contents":[["Prim"],"Number"],"tag":"TypeConstructor"},{"annotation":[],"contents":["scale",{"annotation":[],"contents":[["Prim"],"Number"],"tag":"TypeConstructor"},{"annotation":[],"contents":["turbulence",{"annotation":[],"contents":[["Prim"],"Number"],"tag":"TypeConstructor"},{"annotation":[],"contents":["decay",{"annotation":[],"contents":[["Prim"],"Number"],"tag":"TypeConstructor"},{"annotation":[],"tag":"REmpty"}],"tag":"RCons"}],"tag":"RCons"}],"tag":"RCons"}],"tag":"RCons"}],"tag":"TypeApp"}},"kind":null,"sourceSpan":{"end":[294,4],"name":"src/Lattice/Services/Export/Types.purs","start":[289,1]},"title":"GenerativeFlowParams"},{"children":[],"comments":"A flow layer for composition\n","info":{"arguments":[],"declType":"typeSynonym","type":{"annotation":[],"contents":[{"annotation":[],"contents":[["Prim"],"Record"],"tag":"TypeConstructor"},{"annotation":[],"contents":["trajectory",{"annotation":[],"contents":[["Lattice","Services","Export","Types"],"WanMoveTrajectory"],"tag":"TypeConstructor"},{"annotation":[],"contents":["blendMode",{"annotation":[],"contents":[["Prim"],"String"],"tag":"TypeConstructor"},{"annotation":[],"contents":["opacity",{"annotation":[],"contents":[["Prim"],"Number"],"tag":"TypeConstructor"},{"annotation":[],"tag":"REmpty"}],"tag":"RCons"}],"tag":"RCons"}],"tag":"RCons"}],"tag":"TypeApp"}},"kind":null,"sourceSpan":{"end":[301,4],"name":"src/Lattice/Services/Export/Types.purs","start":[297,1]},"title":"FlowLayer"},{"children":[],"comments":"Force field configuration\n","info":{"arguments":[],"declType":"typeSynonym","type":{"annotation":[],"contents":[{"annotation":[],"contents":[["Prim"],"Record"],"tag":"TypeConstructor"},{"annotation":[],"contents":["forces",{"annotation":[],"contents":[{"annotation":[],"contents":[["Prim"],"Array"],"tag":"TypeConstructor"},{"annotation":[],"contents":[["Lattice","Services","Export","Types"],"ForcePoint"],"tag":"TypeConstructor"}],"tag":"TypeApp"},{"annotation":[],"contents":["strength",{"annotation":[],"contents":[["Prim"],"Number"],"tag":"TypeConstructor"},{"annotation":[],"contents":["falloff",{"annotation":[],"contents":[["Prim"],"Number"],"tag":"TypeConstructor"},{"annotation":[],"tag":"REmpty"}],"tag":"RCons"}],"tag":"RCons"}],"tag":"RCons"}],"tag":"TypeApp"}},"kind":null,"sourceSpan":{"end":[308,4],"name":"src/Lattice/Services/Export/Types.purs","start":[304,1]},"title":"ForceFieldConfig"},{"children":[],"comments":"A single force point\n","info":{"arguments":[],"declType":"typeSynonym","type":{"annotation":[],"contents":[{"annotation":[],"contents":[["Prim"],"Record"],"tag":"TypeConstructor"},{"annotation":[],"contents":["x",{"annotation":[],"contents":[["Prim"],"Number"],"tag":"TypeConstructor"},{"annotation":[],"contents":["y",{"annotation":[],"contents":[["Prim"],"Number"],"tag":"TypeConstructor"},{"annotation":[],"contents":["strength",{"annotation":[],"contents":[["Prim"],"Number"],"tag":"TypeConstructor"},{"annotation":[],"contents":["radius",{"annotation":[],"contents":[["Prim"],"Number"],"tag":"TypeConstructor"},{"annotation":[],"tag":"REmpty"}],"tag":"RCons"}],"tag":"RCons"}],"tag":"RCons"}],"tag":"RCons"}],"tag":"TypeApp"}},"kind":null,"sourceSpan":{"end":[316,4],"name":"src/Lattice/Services/Export/Types.purs","start":[311,1]},"title":"ForcePoint"},{"children":[],"comments":"Strange attractor configuration\n","info":{"arguments":[],"declType":"typeSynonym","type":{"annotation":[],"contents":[{"annotation":[],"contents":[["Prim"],"Record"],"tag":"TypeConstructor"},{"annotation":[],"contents":["type",{"annotation":[],"contents":[["Prim"],"String"],"tag":"TypeConstructor"},{"annotation":[],"contents":["sigma",{"annotation":[],"contents":[["Prim"],"Number"],"tag":"TypeConstructor"},{"annotation":[],"contents":["rho",{"annotation":[],"contents":[["Prim"],"Number"],"tag":"TypeConstructor"},{"annotation":[],"contents":["beta",{"annotation":[],"contents":[["Prim"],"Number"],"tag":"TypeConstructor"},{"annotation":[],"contents":["scale",{"annotation":[],"contents":[["Prim"],"Number"],"tag":"TypeConstructor"},{"annotation":[],"tag":"REmpty"}],"tag":"RCons"}],"tag":"RCons"}],"tag":"RCons"}],"tag":"RCons"}],"tag":"RCons"}],"tag":"TypeApp"}},"kind":null,"sourceSpan":{"end":[325,4],"name":"src/Lattice/Services/Export/Types.purs","start":[319,1]},"title":"AttractorConfig"},{"children":[],"comments":"Colored trajectory\n","info":{"arguments":[],"declType":"typeSynonym","type":{"annotation":[],"contents":[{"annotation":[],"contents":[["Prim"],"Record"],"tag":"TypeConstructor"},{"annotation":[],"contents":["trajectory",{"annotation":[],"contents":[["Lattice","Services","Export","Types"],"WanMoveTrajectory"],"tag":"TypeConstructor"},{"annotation":[],"contents":["colors",{"annotation":[],"contents":[{"annotation":[],"contents":[["Prim"],"Array"],"tag":"TypeConstructor"},{"annotation":[],"contents":[["Prim"],"String"],"tag":"TypeConstructor"}],"tag":"TypeApp"},{"annotation":[],"tag":"REmpty"}],"tag":"RCons"}],"tag":"RCons"}],"tag":"TypeApp"}},"kind":null,"sourceSpan":{"end":[335,4],"name":"src/Lattice/Services/Export/Types.purs","start":[332,1]},"title":"ColoredTrajectory"},{"children":[],"comments":"Color gradient for trajectory visualization\n","info":{"arguments":[],"declType":"typeSynonym","type":{"annotation":[],"contents":[{"annotation":[],"contents":[["Prim"],"Record"],"tag":"TypeConstructor"},{"annotation":[],"contents":["name",{"annotation":[],"contents":[["Prim"],"String"],"tag":"TypeConstructor"},{"annotation":[],"contents":["stops",{"annotation":[],"contents":[{"annotation":[],"contents":[["Prim"],"Array"],"tag":"TypeConstructor"},{"annotation":[],"contents":[{"annotation":[],"contents":[["Prim"],"Record"],"tag":"TypeConstructor"},{"annotation":[],"contents":["position",{"annotation":[],"contents":[["Prim"],"Number"],"tag":"TypeConstructor"},{"annotation":[],"contents":["color",{"annotation":[],"contents":[["Prim"],"String"],"tag":"TypeConstructor"},{"annotation":[],"tag":"REmpty"}],"tag":"RCons"}],"tag":"RCons"}],"tag":"TypeApp"}],"tag":"TypeApp"},{"annotation":[],"tag":"REmpty"}],"tag":"RCons"}],"tag":"RCons"}],"tag":"TypeApp"}},"kind":null,"sourceSpan":{"end":[341,4],"name":"src/Lattice/Services/Export/Types.purs","start":[338,1]},"title":"ColorGradient"},{"children":[],"comments":"Video encoder configuration\n","info":{"arguments":[],"declType":"typeSynonym","type":{"annotation":[],"contents":[{"annotation":[],"contents":[["Prim"],"Record"],"tag":"TypeConstructor"},{"annotation":[],"contents":["codec",{"annotation":[],"contents":[["Prim"],"String"],"tag":"TypeConstructor"},{"annotation":[],"contents":["width",{"annotation":[],"contents":[["Prim"],"Int"],"tag":"TypeConstructor"},{"annotation":[],"contents":["height",{"annotation":[],"contents":[["Prim"],"Int"],"tag":"TypeConstructor"},{"annotation":[],"contents":["frameRate",{"annotation":[],"contents":[["Prim"],"Int"],"tag":"TypeConstructor"},{"annotation":[],"contents":["bitrate",{"annotation":[],"contents":[["Prim"],"Int"],"tag":"TypeConstructor"},{"annotation":[],"contents":["keyFrameInterval",{"annotation":[],"contents":[["Prim"],"Int"],"tag":"TypeConstructor"},{"annotation":[],"tag":"REmpty"}],"tag":"RCons"}],"tag":"RCons"}],"tag":"RCons"}],"tag":"RCons"}],"tag":"RCons"}],"tag":"RCons"}],"tag":"TypeApp"}},"kind":null,"sourceSpan":{"end":[355,4],"name":"src/Lattice/Services/Export/Types.purs","start":[348,1]},"title":"VideoEncoderConfig"},{"children":[],"comments":"Encoded video result\n","info":{"arguments":[],"declType":"typeSynonym","type":{"annotation":[],"contents":[{"annotation":[],"contents":[["Prim"],"Record"],"tag":"TypeConstructor"},{"annotation":[],"contents":["blob",{"annotation":[],"contents":[["Prim"],"String"],"tag":"TypeConstructor"},{"annotation":[],"contents":["duration",{"annotation":[],"contents":[["Prim"],"Number"],"tag":"TypeConstructor"},{"annotation":[],"contents":["size",{"annotation":[],"contents":[["Prim"],"Int"],"tag":"TypeConstructor"},{"annotation":[],"contents":["codec",{"annotation":[],"contents":[["Prim"],"String"],"tag":"TypeConstructor"},{"annotation":[],"tag":"REmpty"}],"tag":"RCons"}],"tag":"RCons"}],"tag":"RCons"}],"tag":"RCons"}],"tag":"TypeApp"}},"kind":null,"sourceSpan":{"end":[363,4],"name":"src/Lattice/Services/Export/Types.purs","start":[358,1]},"title":"EncodedVideo"},{"children":[],"comments":"Encoding progress\n","info":{"arguments":[],"declType":"typeSynonym","type":{"annotation":[],"contents":[{"annotation":[],"contents":[["Prim"],"Record"],"tag":"TypeConstructor"},{"annotation":[],"contents":["framesEncoded",{"annotation":[],"contents":[["Prim"],"Int"],"tag":"TypeConstructor"},{"annotation":[],"contents":["totalFrames",{"annotation":[],"contents":[["Prim"],"Int"],"tag":"TypeConstructor"},{"annotation":[],"contents":["percentage",{"annotation":[],"contents":[["Prim"],"Number"],"tag":"TypeConstructor"},{"annotation":[],"contents":["bytesWritten",{"annotation":[],"contents":[["Prim"],"Int"],"tag":"TypeConstructor"},{"annotation":[],"tag":"REmpty"}],"tag":"RCons"}],"tag":"RCons"}],"tag":"RCons"}],"tag":"RCons"}],"tag":"TypeApp"}},"kind":null,"sourceSpan":{"end":[371,4],"name":"src/Lattice/Services/Export/Types.purs","start":[366,1]},"title":"EncodingProgress"},{"children":[],"comments":"VACE export configuration\n","info":{"arguments":[],"declType":"typeSynonym","type":{"annotation":[],"contents":[{"annotation":[],"contents":[["Prim"],"Record"],"tag":"TypeConstructor"},{"annotation":[],"contents":["resolution",{"annotation":[],"contents":[{"annotation":[],"contents":[["Prim"],"Record"],"tag":"TypeConstructor"},{"annotation":[],"contents":["width",{"annotation":[],"contents":[["Prim"],"Int"],"tag":"TypeConstructor"},{"annotation":[],"contents":["height",{"annotation":[],"contents":[["Prim"],"Int"],"tag":"TypeConstructor"},{"annotation":[],"tag":"REmpty"}],"tag":"RCons"}],"tag":"RCons"}],"tag":"TypeApp"},{"annotation":[],"contents":["frameRate",{"annotation":[],"contents":[["Prim"],"Int"],"tag":"TypeConstructor"},{"annotation":[],"contents":["frameCount",{"annotation":[],"contents":[["Prim"],"Int"],"tag":"TypeConstructor"},{"annotation":[],"contents":["backgroundColor",{"annotation":[],"contents":[["Prim"],"String"],"tag":"TypeConstructor"},{"annotation":[],"tag":"REmpty"}],"tag":"RCons"}],"tag":"RCons"}],"tag":"RCons"}],"tag":"RCons"}],"tag":"TypeApp"}},"kind":null,"sourceSpan":{"end":[383,4],"name":"src/Lattice/Services/Export/Types.purs","start":[378,1]},"title":"VACEExportConfig"},{"children":[],"comments":"A single VACE frame\n","info":{"arguments":[],"declType":"typeSynonym","type":{"annotation":[],"contents":[{"annotation":[],"contents":[["Prim"],"Record"],"tag":"TypeConstructor"},{"annotation":[],"contents":["frameNumber",{"annotation":[],"contents":[["Prim"],"Int"],"tag":"TypeConstructor"},{"annotation":[],"contents":["shapes",{"annotation":[],"contents":[{"annotation":[],"contents":[["Prim"],"Array"],"tag":"TypeConstructor"},{"annotation":[],"contents":[{"annotation":[],"contents":[["Prim"],"Record"],"tag":"TypeConstructor"},{"annotation":[],"contents":["path",{"annotation":[],"contents":[["Prim"],"String"],"tag":"TypeConstructor"},{"annotation":[],"contents":["fill",{"annotation":[],"contents":[["Prim"],"String"],"tag":"TypeConstructor"},{"annotation":[],"contents":["stroke",{"annotation":[],"contents":[{"annotation":[],"contents":[["Data","Maybe"],"Maybe"],"tag":"TypeConstructor"},{"annotation":[],"contents":[["Prim"],"String"],"tag":"TypeConstructor"}],"tag":"TypeApp"},{"annotation":[],"contents":["transform",{"annotation":[],"contents":[["Prim"],"String"],"tag":"TypeConstructor"},{"annotation":[],"tag":"REmpty"}],"tag":"RCons"}],"tag":"RCons"}],"tag":"RCons"}],"tag":"RCons"}],"tag":"TypeApp"}],"tag":"TypeApp"},{"annotation":[],"tag":"REmpty"}],"tag":"RCons"}],"tag":"RCons"}],"tag":"TypeApp"}},"kind":null,"sourceSpan":{"end":[394,4],"name":"src/Lattice/Services/Export/Types.purs","start":[386,1]},"title":"VACEFrame"},{"children":[],"comments":"Path follower configuration\n","info":{"arguments":[],"declType":"typeSynonym","type":{"annotation":[],"contents":[{"annotation":[],"contents":[["Prim"],"Record"],"tag":"TypeConstructor"},{"annotation":[],"contents":["speed",{"annotation":[],"contents":[["Prim"],"Number"],"tag":"TypeConstructor"},{"annotation":[],"contents":["easing",{"annotation":[],"contents":[["Lattice","Services","Export","Types"],"PathFollowerEasing"],"tag":"TypeConstructor"},{"annotation":[],"contents":["loop",{"annotation":[],"contents":[["Prim"],"Boolean"],"tag":"TypeConstructor"},{"annotation":[],"contents":["pingPong",{"annotation":[],"contents":[["Prim"],"Boolean"],"tag":"TypeConstructor"},{"annotation":[],"tag":"REmpty"}],"tag":"RCons"}],"tag":"RCons"}],"tag":"RCons"}],"tag":"RCons"}],"tag":"TypeApp"}},"kind":null,"sourceSpan":{"end":[402,4],"name":"src/Lattice/Services/Export/Types.purs","start":[397,1]},"title":"PathFollowerConfig"},{"children":[],"comments":"Path follower state\n","info":{"arguments":[],"declType":"typeSynonym","type":{"annotation":[],"contents":[{"annotation":[],"contents":[["Prim"],"Record"],"tag":"TypeConstructor"},{"annotation":[],"contents":["progress",{"annotation":[],"contents":[["Prim"],"Number"],"tag":"TypeConstructor"},{"annotation":[],"contents":["position",{"annotation":[],"contents":[{"annotation":[],"contents":[["Prim"],"Record"],"tag":"TypeConstructor"},{"annotation":[],"contents":["x",{"annotation":[],"contents":[["Prim"],"Number"],"tag":"TypeConstructor"},{"annotation":[],"contents":["y",{"annotation":[],"contents":[["Prim"],"Number"],"tag":"TypeConstructor"},{"annotation":[],"tag":"REmpty"}],"tag":"RCons"}],"tag":"RCons"}],"tag":"TypeApp"},{"annotation":[],"contents":["rotation",{"annotation":[],"contents":[["Prim"],"Number"],"tag":"TypeConstructor"},{"annotation":[],"contents":["scale",{"annotation":[],"contents":[["Prim"],"Number"],"tag":"TypeConstructor"},{"annotation":[],"tag":"REmpty"}],"tag":"RCons"}],"tag":"RCons"}],"tag":"RCons"}],"tag":"RCons"}],"tag":"TypeApp"}},"kind":null,"sourceSpan":{"end":[410,4],"name":"src/Lattice/Services/Export/Types.purs","start":[405,1]},"title":"PathFollowerState"},{"children":[{"comments":null,"info":{"arguments":[{"annotation":[],"contents":[["Prim"],"Number"],"tag":"TypeConstructor"}],"declType":"dataConstructor"},"sourceSpan":{"end":[414,16],"name":"src/Lattice/Services/Export/Types.purs","start":[414,3]},"title":"ShapeCircle"},{"comments":null,"info":{"arguments":[{"annotation":[],"contents":[["Prim"],"Number"],"tag":"TypeConstructor"},{"annotation":[],"contents":[["Prim"],"Number"],"tag":"TypeConstructor"}],"declType":"dataConstructor"},"sourceSpan":{"end":[415,19],"name":"src/Lattice/Services/Export/Types.purs","start":[415,3]},"title":"ShapeRectangle"},{"comments":null,"info":{"arguments":[{"annotation":[],"contents":[["Prim"],"Number"],"tag":"TypeConstructor"}],"declType":"dataConstructor"},"sourceSpan":{"end":[416,18],"name":"src/Lattice/Services/Export/Types.purs","start":[416,3]},"title":"ShapeTriangle"},{"comments":null,"info":{"arguments":[{"annotation":[],"contents":[["Prim"],"String"],"tag":"TypeConstructor"}],"declType":"dataConstructor"},"sourceSpan":{"end":[417,19],"name":"src/Lattice/Services/Export/Types.purs","start":[417,3]},"title":"ShapeCustomSVG"},{"comments":null,"info":{"declType":"instance","dependencies":[],"type":{"annotation":[],"contents":[{"annotation":[],"contents":[{"annotation":[],"contents":[["Data","Generic","Rep"],"Generic"],"tag":"TypeConstructor"},{"annotation":[],"contents":[["Lattice","Services","Export","Types"],"PathFollowerShape"],"tag":"TypeConstructor"}],"tag":"TypeApp"},{"annotation":[],"contents":null,"tag":"TypeWildcard"}],"tag":"TypeApp"}},"sourceSpan":{"end":[419,44],"name":"src/Lattice/Services/Export/Types.purs","start":[419,1]},"title":"<anonymous>"},{"comments":null,"info":{"declType":"instance","dependencies":[],"type":{"annotation":[],"contents":[{"annotation":[],"contents":[["Data","Show"],"Show"],"tag":"TypeConstructor"},{"annotation":[],"contents":[["Lattice","Services","Export","Types"],"PathFollowerShape"],"tag":"TypeConstructor"}],"tag":"TypeApp"}},"sourceSpan":{"end":[420,57],"name":"src/Lattice/Services/Export/Types.purs","start":[420,1]},"title":"<anonymous>"},{"comments":null,"info":{"declType":"instance","dependencies":[],"type":{"annotation":[],"contents":[{"annotation":[],"contents":[["Data","Eq"],"Eq"],"tag":"TypeConstructor"},{"annotation":[],"contents":[["Lattice","Services","Export","Types"],"PathFollowerShape"],"tag":"TypeConstructor"}],"tag":"TypeApp"}},"sourceSpan":{"end":[421,51],"name":"src/Lattice/Services/Export/Types.purs","start":[421,1]},"title":"<anonymous>"}],"comments":"Path follower shape types\n","info":{"dataDeclType":"data","declType":"data","roles":[],"typeArguments":[]},"kind":null,"sourceSpan":{"end":[417,26],"name":"src/Lattice/Services/Export/Types.purs","start":[413,1]},"title":"PathFollowerShape"},{"children":[{"comments":null,"info":{"arguments":[],"declType":"dataConstructor"},"sourceSpan":{"end":[425,15],"name":"src/Lattice/Services/Export/Types.purs","start":[425,3]},"title":"EaseLinear"},{"comments":null,"info":{"arguments":[],"declType":"dataConstructor"},"sourceSpan":{"end":[426,14],"name":"src/Lattice/Services/Export/Types.purs","start":[426,3]},"title":"EaseInOut"},{"comments":null,"info":{"arguments":[],"declType":"dataConstructor"},"sourceSpan":{"end":[427,11],"name":"src/Lattice/Services/Export/Types.purs","start":[427,3]},"title":"EaseIn"},{"comments":null,"info":{"arguments":[],"declType":"dataConstructor"},"sourceSpan":{"end":[428,12],"name":"src/Lattice/Services/Export/Types.purs","start":[428,3]},"title":"EaseOut"},{"comments":null,"info":{"arguments":[],"declType":"dataConstructor"},"sourceSpan":{"end":[429,15],"name":"src/Lattice/Services/Export/Types.purs","start":[429,3]},"title":"EaseBounce"},{"comments":null,"info":{"declType":"instance","dependencies":[],"type":{"annotation":[],"contents":[{"annotation":[],"contents":[{"annotation":[],"contents":[["Data","Generic","Rep"],"Generic"],"tag":"TypeConstructor"},{"annotation":[],"contents":[["Lattice","Services","Export","Types"],"PathFollowerEasing"],"tag":"TypeConstructor"}],"tag":"TypeApp"},{"annotation":[],"contents":null,"tag":"TypeWildcard"}],"tag":"TypeApp"}},"sourceSpan":{"end":[431,45],"name":"src/Lattice/Services/Export/Types.purs","start":[431,1]},"title":"<anonymous>"},{"comments":null,"info":{"declType":"instance","dependencies":[],"type":{"annotation":[],"contents":[{"annotation":[],"contents":[["Data","Show"],"Show"],"tag":"TypeConstructor"},{"annotation":[],"contents":[["Lattice","Services","Export","Types"],"PathFollowerEasing"],"tag":"TypeConstructor"}],"tag":"TypeApp"}},"sourceSpan":{"end":[432,58],"name":"src/Lattice/Services/Export/Types.purs","start":[432,1]},"title":"<anonymous>"},{"comments":null,"info":{"declType":"instance","dependencies":[],"type":{"annotation":[],"contents":[{"annotation":[],"contents":[["Data","Eq"],"Eq"],"tag":"TypeConstructor"},{"annotation":[],"contents":[["Lattice","Services","Export","Types"],"PathFollowerEasing"],"tag":"TypeConstructor"}],"tag":"TypeApp"}},"sourceSpan":{"end":[433,52],"name":"src/Lattice/Services/Export/Types.purs","start":[433,1]},"title":"<anonymous>"}],"comments":"Path follower easing\n","info":{"dataDeclType":"data","declType":"data","roles":[],"typeArguments":[]},"kind":null,"sourceSpan":{"end":[429,15],"name":"src/Lattice/Services/Export/Types.purs","start":[424,1]},"title":"PathFollowerEasing"},{"children":[],"comments":"Composition info for mesh export\n","info":{"arguments":[],"declType":"typeSynonym","type":{"annotation":[],"contents":[{"annotation":[],"contents":[["Prim"],"Record"],"tag":"TypeConstructor"},{"annotation":[],"contents":["width",{"annotation":[],"contents":[["Prim"],"Int"],"tag":"TypeConstructor"},{"annotation":[],"contents":["height",{"annotation":[],"contents":[["Prim"],"Int"],"tag":"TypeConstructor"},{"annotation":[],"contents":["frameRate",{"annotation":[],"contents":[["Prim"],"Int"],"tag":"TypeConstructor"},{"annotation":[],"contents":["duration",{"annotation":[],"contents":[["Prim"],"Number"],"tag":"TypeConstructor"},{"annotation":[],"tag":"REmpty"}],"tag":"RCons"}],"tag":"RCons"}],"tag":"RCons"}],"tag":"RCons"}],"tag":"TypeApp"}},"kind":null,"sourceSpan":{"end":[445,4],"name":"src/Lattice/Services/Export/Types.purs","start":[440,1]},"title":"CompositionInfo"},{"children":[],"comments":"Mesh mask export\n","info":{"arguments":[],"declType":"typeSynonym","type":{"annotation":[],"contents":[{"annotation":[],"contents":[["Prim"],"Record"],"tag":"TypeConstructor"},{"annotation":[],"contents":["mask",{"annotation":[],"contents":[["Prim"],"String"],"tag":"TypeConstructor"},{"annotation":[],"contents":["width",{"annotation":[],"contents":[["Prim"],"Int"],"tag":"TypeConstructor"},{"annotation":[],"contents":["height",{"annotation":[],"contents":[["Prim"],"Int"],"tag":"TypeConstructor"},{"annotation":[],"contents":["frameNumber",{"annotation":[],"contents":[["Prim"],"Int"],"tag":"TypeConstructor"},{"annotation":[],"tag":"REmpty"}],"tag":"RCons"}],"tag":"RCons"}],"tag":"RCons"}],"tag":"RCons"}],"tag":"TypeApp"}},"kind":null,"sourceSpan":{"end":[453,4],"name":"src/Lattice/Services/Export/Types.purs","start":[448,1]},"title":"MeshMaskExport"},{"children":[],"comments":"4x4 camera matrix\n","info":{"arguments":[],"declType":"typeSynonym","type":{"annotation":[],"contents":[{"annotation":[],"contents":[["Prim"],"Array"],"tag":"TypeConstructor"},{"annotation":[],"contents":{"annotation":[],"contents":[{"annotation":[],"contents":[["Prim"],"Array"],"tag":"TypeConstructor"},{"annotation":[],"contents":[["Prim"],"Number"],"tag":"TypeConstructor"}],"tag":"TypeApp"},"tag":"ParensInType"}],"tag":"TypeApp"}},"kind":null,"sourceSpan":{"end":[460,44],"name":"src/Lattice/Services/Export/Types.purs","start":[460,1]},"title":"CameraMatrix4x4"},{"children":[],"comments":"Camera trajectory export\n","info":{"arguments":[],"declType":"typeSynonym","type":{"annotation":[],"contents":[{"annotation":[],"contents":[["Prim"],"Record"],"tag":"TypeConstructor"},{"annotation":[],"contents":["matrices",{"annotation":[],"contents":[{"annotation":[],"contents":[["Prim"],"Array"],"tag":"TypeConstructor"},{"annotation":[],"contents":[["Lattice","Services","Export","Types"],"CameraMatrix4x4"],"tag":"TypeConstructor"}],"tag":"TypeApp"},{"annotation":[],"contents":["frameCount",{"annotation":[],"contents":[["Prim"],"Int"],"tag":"TypeConstructor"},{"annotation":[],"contents":["intrinsics",{"annotation":[],"contents":[{"annotation":[],"contents":[["Prim"],"Record"],"tag":"TypeConstructor"},{"annotation":[],"contents":["fx",{"annotation":[],"contents":[["Prim"],"Number"],"tag":"TypeConstructor"},{"annotation":[],"contents":["fy",{"annotation":[],"contents":[["Prim"],"Number"],"tag":"TypeConstructor"},{"annotation":[],"contents":["cx",{"annotation":[],"contents":[["Prim"],"Number"],"tag":"TypeConstructor"},{"annotation":[],"contents":["cy",{"annotation":[],"contents":[["Prim"],"Number"],"tag":"TypeConstructor"},{"annotation":[],"tag":"REmpty"}],"tag":"RCons"}],"tag":"RCons"}],"tag":"RCons"}],"tag":"RCons"}],"tag":"TypeApp"},{"annotation":[],"tag":"REmpty"}],"tag":"RCons"}],"tag":"RCons"}],"tag":"RCons"}],"tag":"TypeApp"}},"kind":null,"sourceSpan":{"end":[467,4],"name":"src/Lattice/Services/Export/Types.purs","start":[463,1]},"title":"CameraTrajectoryExport"},{"children":[],"comments":"CameraCtrl pose entry\n","info":{"arguments":[],"declType":"typeSynonym","type":{"annotation":[],"contents":[{"annotation":[],"contents":[["Prim"],"Record"],"tag":"TypeConstructor"},{"annotation":[],"contents":["rotation",{"annotation":[],"contents":[{"annotation":[],"contents":[["Prim"],"Array"],"tag":"TypeConstructor"},{"annotation":[],"contents":[["Prim"],"Number"],"tag":"TypeConstructor"}],"tag":"TypeApp"},{"annotation":[],"contents":["translation",{"annotation":[],"contents":[{"annotation":[],"contents":[["Prim"],"Array"],"tag":"TypeConstructor"},{"annotation":[],"contents":[["Prim"],"Number"],"tag":"TypeConstructor"}],"tag":"TypeApp"},{"annotation":[],"contents":["frame",{"annotation":[],"contents":[["Prim"],"Int"],"tag":"TypeConstructor"},{"annotation":[],"tag":"REmpty"}],"tag":"RCons"}],"tag":"RCons"}],"tag":"RCons"}],"tag":"TypeApp"}},"kind":null,"sourceSpan":{"end":[474,4],"name":"src/Lattice/Services/Export/Types.purs","start":[470,1]},"title":"CameraCtrlPoseEntry"},{"children":[],"comments":"Uni3C frame\n","info":{"arguments":[],"declType":"typeSynonym","type":{"annotation":[],"contents":[{"annotation":[],"contents":[["Prim"],"Record"],"tag":"TypeConstructor"},{"annotation":[],"contents":["timestamp",{"annotation":[],"contents":[["Prim"],"Number"],"tag":"TypeConstructor"},{"annotation":[],"contents":["rotation",{"annotation":[],"contents":[{"annotation":[],"contents":[["Prim"],"Array"],"tag":"TypeConstructor"},{"annotation":[],"contents":[["Prim"],"Number"],"tag":"TypeConstructor"}],"tag":"TypeApp"},{"annotation":[],"contents":["translation",{"annotation":[],"contents":[{"annotation":[],"contents":[["Prim"],"Array"],"tag":"TypeConstructor"},{"annotation":[],"contents":[["Prim"],"Number"],"tag":"TypeConstructor"}],"tag":"TypeApp"},{"annotation":[],"contents":["fov",{"annotation":[],"contents":[["Prim"],"Number"],"tag":"TypeConstructor"},{"annotation":[],"tag":"REmpty"}],"tag":"RCons"}],"tag":"RCons"}],"tag":"RCons"}],"tag":"RCons"}],"tag":"TypeApp"}},"kind":null,"sourceSpan":{"end":[482,4],"name":"src/Lattice/Services/Export/Types.purs","start":[477,1]},"title":"Uni3CFrame"},{"children":[],"comments":"Uni3C track\n","info":{"arguments":[],"declType":"typeSynonym","type":{"annotation":[],"contents":[{"annotation":[],"contents":[["Prim"],"Record"],"tag":"TypeConstructor"},{"annotation":[],"contents":["frames",{"annotation":[],"contents":[{"annotation":[],"contents":[["Prim"],"Array"],"tag":"TypeConstructor"},{"annotation":[],"contents":[["Lattice","Services","Export","Types"],"Uni3CFrame"],"tag":"TypeConstructor"}],"tag":"TypeApp"},{"annotation":[],"contents":["intrinsics",{"annotation":[],"contents":[{"annotation":[],"contents":[["Prim"],"Record"],"tag":"TypeConstructor"},{"annotation":[],"contents":["fx",{"annotation":[],"contents":[["Prim"],"Number"],"tag":"TypeConstructor"},{"annotation":[],"contents":["fy",{"annotation":[],"contents":[["Prim"],"Number"],"tag":"TypeConstructor"},{"annotation":[],"contents":["cx",{"annotation":[],"contents":[["Prim"],"Number"],"tag":"TypeConstructor"},{"annotation":[],"contents":["cy",{"annotation":[],"contents":[["Prim"],"Number"],"tag":"TypeConstructor"},{"annotation":[],"tag":"REmpty"}],"tag":"RCons"}],"tag":"RCons"}],"tag":"RCons"}],"tag":"RCons"}],"tag":"TypeApp"},{"annotation":[],"tag":"REmpty"}],"tag":"RCons"}],"tag":"RCons"}],"tag":"TypeApp"}},"kind":null,"sourceSpan":{"end":[488,4],"name":"src/Lattice/Services/Export/Types.purs","start":[485,1]},"title":"Uni3CTrack"},{"children":[{"comments":null,"info":{"arguments":[],"declType":"dataConstructor"},"sourceSpan":{"end":[496,18],"name":"src/Lattice/Services/Export/Types.purs","start":[496,3]},"title":"TargetWanMove"},{"comments":null,"info":{"arguments":[],"declType":"dataConstructor"},"sourceSpan":{"end":[497,14],"name":"src/Lattice/Services/Export/Types.purs","start":[497,3]},"title":"TargetATI"},{"comments":null,"info":{"arguments":[],"declType":"dataConstructor"},"sourceSpan":{"end":[498,17],"name":"src/Lattice/Services/Export/Types.purs","start":[498,3]},"title":"TargetLightX"},{"comments":null,"info":{"arguments":[],"declType":"dataConstructor"},"sourceSpan":{"end":[499,14],"name":"src/Lattice/Services/Export/Types.purs","start":[499,3]},"title":"TargetTTM"},{"comments":null,"info":{"arguments":[],"declType":"dataConstructor"},"sourceSpan":{"end":[500,16],"name":"src/Lattice/Services/Export/Types.purs","start":[500,3]},"title":"TargetSCAIL"},{"comments":null,"info":{"arguments":[],"declType":"dataConstructor"},"sourceSpan":{"end":[501,24],"name":"src/Lattice/Services/Export/Types.purs","start":[501,3]},"title":"TargetCameraComfyUI"},{"comments":null,"info":{"arguments":[],"declType":"dataConstructor"},"sourceSpan":{"end":[502,21],"name":"src/Lattice/Services/Export/Types.purs","start":[502,3]},"title":"TargetMotionCtrl"},{"comments":null,"info":{"arguments":[],"declType":"dataConstructor"},"sourceSpan":{"end":[503,16],"name":"src/Lattice/Services/Export/Types.purs","start":[503,3]},"title":"TargetUni3C"},{"comments":null,"info":{"declType":"instance","dependencies":[],"type":{"annotation":[],"contents":[{"annotation":[],"contents":[{"annotation":[],"contents":[["Data","Generic","Rep"],"Generic"],"tag":"TypeConstructor"},{"annotation":[],"contents":[["Lattice","Services","Export","Types"],"ModelTarget"],"tag":"TypeConstructor"}],"tag":"TypeApp"},{"annotation":[],"contents":null,"tag":"TypeWildcard"}],"tag":"TypeApp"}},"sourceSpan":{"end":[505,38],"name":"src/Lattice/Services/Export/Types.purs","start":[505,1]},"title":"<anonymous>"},{"comments":null,"info":{"declType":"instance","dependencies":[],"type":{"annotation":[],"contents":[{"annotation":[],"contents":[["Data","Show"],"Show"],"tag":"TypeConstructor"},{"annotation":[],"contents":[["Lattice","Services","Export","Types"],"ModelTarget"],"tag":"TypeConstructor"}],"tag":"TypeApp"}},"sourceSpan":{"end":[506,51],"name":"src/Lattice/Services/Export/Types.purs","start":[506,1]},"title":"<anonymous>"},{"comments":null,"info":{"declType":"instance","dependencies":[],"type":{"annotation":[],"contents":[{"annotation":[],"contents":[["Data","Eq"],"Eq"],"tag":"TypeConstructor"},{"annotation":[],"contents":[["Lattice","Services","Export","Types"],"ModelTarget"],"tag":"TypeConstructor"}],"tag":"TypeApp"}},"sourceSpan":{"end":[507,45],"name":"src/Lattice/Services/Export/Types.purs","start":[507,1]},"title":"<anonymous>"}],"comments":"Supported model targets\n","info":{"dataDeclType":"data","declType":"data","roles":[],"typeArguments":[]},"kind":null,"sourceSpan":{"end":[503,16],"name":"src/Lattice/Services/Export/Types.purs","start":[495,1]},"title":"ModelTarget"},{"children":[],"comments":"Unified export options\n","info":{"arguments":[],"declType":"typeSynonym","type":{"annotation":[],"contents":[{"annotation":[],"contents":[["Prim"],"Record"],"tag":"TypeConstructor"},{"annotation":[],"contents":["target",{"annotation":[],"contents":[["Lattice","Services","Export","Types"],"ModelTarget"],"tag":"TypeConstructor"},{"annotation":[],"contents":["width",{"annotation":[],"contents":[["Prim"],"Int"],"tag":"TypeConstructor"},{"annotation":[],"contents":["height",{"annotation":[],"contents":[["Prim"],"Int"],"tag":"TypeConstructor"},{"annotation":[],"contents":["frameCount",{"annotation":[],"contents":[["Prim"],"Int"],"tag":"TypeConstructor"},{"annotation":[],"contents":["frameRate",{"annotation":[],"contents":[["Prim"],"Int"],"tag":"TypeConstructor"},{"annotation":[],"contents":["layers",{"annotation":[],"contents":[{"annotation":[],"contents":[["Prim"],"Array"],"tag":"TypeConstructor"},{"annotation":[],"contents":[["Prim"],"String"],"tag":"TypeConstructor"}],"tag":"TypeApp"},{"annotation":[],"contents":["splines",{"annotation":[],"contents":[{"annotation":[],"contents":[["Prim"],"Array"],"tag":"TypeConstructor"},{"annotation":[],"contents":[["Prim"],"String"],"tag":"TypeConstructor"}],"tag":"TypeApp"},{"annotation":[],"contents":["includeCamera",{"annotation":[],"contents":[["Prim"],"Boolean"],"tag":"TypeConstructor"},{"annotation":[],"contents":["includeDepth",{"annotation":[],"contents":[["Prim"],"Boolean"],"tag":"TypeConstructor"},{"annotation":[],"tag":"REmpty"}],"tag":"RCons"}],"tag":"RCons"}],"tag":"RCons"}],"tag":"RCons"}],"tag":"RCons"}],"tag":"RCons"}],"tag":"RCons"}],"tag":"RCons"}],"tag":"RCons"}],"tag":"TypeApp"}},"kind":null,"sourceSpan":{"end":[520,4],"name":"src/Lattice/Services/Export/Types.purs","start":[510,1]},"title":"UnifiedExportOptions"},{"children":[],"comments":"Unified export result\n","info":{"arguments":[],"declType":"typeSynonym","type":{"annotation":[],"contents":[{"annotation":[],"contents":[["Prim"],"Record"],"tag":"TypeConstructor"},{"annotation":[],"contents":["success",{"annotation":[],"contents":[["Prim"],"Boolean"],"tag":"TypeConstructor"},{"annotation":[],"contents":["target",{"annotation":[],"contents":[["Lattice","Services","Export","Types"],"ModelTarget"],"tag":"TypeConstructor"},{"annotation":[],"contents":["data",{"annotation":[],"contents":[{"annotation":[],"contents":[["Data","Maybe"],"Maybe"],"tag":"TypeConstructor"},{"annotation":[],"contents":[["Lattice","Services","Export","Types"],"WanMoveTrajectory"],"tag":"TypeConstructor"}],"tag":"TypeApp"},{"annotation":[],"contents":["camera",{"annotation":[],"contents":[{"annotation":[],"contents":[["Data","Maybe"],"Maybe"],"tag":"TypeConstructor"},{"annotation":[],"contents":[["Lattice","Services","Export","Types"],"CameraTrajectoryExport"],"tag":"TypeConstructor"}],"tag":"TypeApp"},{"annotation":[],"contents":["depth",{"annotation":[],"contents":[{"annotation":[],"contents":[["Data","Maybe"],"Maybe"],"tag":"TypeConstructor"},{"annotation":[],"contents":{"annotation":[],"contents":[{"annotation":[],"contents":[["Prim"],"Array"],"tag":"TypeConstructor"},{"annotation":[],"contents":[["Prim"],"String"],"tag":"TypeConstructor"}],"tag":"TypeApp"},"tag":"ParensInType"}],"tag":"TypeApp"},{"annotation":[],"contents":["error",{"annotation":[],"contents":[{"annotation":[],"contents":[["Data","Maybe"],"Maybe"],"tag":"TypeConstructor"},{"annotation":[],"contents":[["Prim"],"String"],"tag":"TypeConstructor"}],"tag":"TypeApp"},{"annotation":[],"tag":"REmpty"}],"tag":"RCons"}],"tag":"RCons"}],"tag":"RCons"}],"tag":"RCons"}],"tag":"RCons"}],"tag":"RCons"}],"tag":"TypeApp"}},"kind":null,"sourceSpan":{"end":[530,4],"name":"src/Lattice/Services/Export/Types.purs","start":[523,1]},"title":"UnifiedExportResult"}],"name":"Lattice.Services.Export.Types","reExports":[]}