{"comments":"Lattice.Services.Physics.VectorMath - 2D Vector Math Operations\n\nPure mathematical functions for 2D vector operations used in physics\nsimulation. All operations are deterministic and side-effect free.\n\nOperations:\n- Basic: add, sub, scale, negate\n- Products: dot, cross (2D pseudo-cross)\n- Metrics: length, lengthSq, distance, distanceSq\n- Normalization and rotation\n- Interpolation: lerp\n\nSource: ui/src/services/physics/PhysicsEngine.ts\n","declarations":[{"children":[],"comments":"2D Vector for physics calculations\n","info":{"arguments":[],"declType":"typeSynonym","type":{"annotation":[],"contents":[{"annotation":[],"contents":[["Prim"],"Record"],"tag":"TypeConstructor"},{"annotation":[],"contents":["x",{"annotation":[],"contents":[["Prim"],"Number"],"tag":"TypeConstructor"},{"annotation":[],"contents":["y",{"annotation":[],"contents":[["Prim"],"Number"],"tag":"TypeConstructor"},{"annotation":[],"tag":"REmpty"}],"tag":"RCons"}],"tag":"RCons"}],"tag":"TypeApp"}},"kind":null,"sourceSpan":{"end":[52,4],"name":"src/Lattice/Services/Physics/VectorMath.purs","start":[49,1]},"title":"Vec2"},{"children":[],"comments":"Create a zero vector\n","info":{"declType":"value","type":{"annotation":[],"contents":[["Lattice","Services","Physics","VectorMath"],"Vec2"],"tag":"TypeConstructor"}},"kind":null,"sourceSpan":{"end":[59,13],"name":"src/Lattice/Services/Physics/VectorMath.purs","start":[59,1]},"title":"zero"},{"children":[],"comments":"Create a vector from components\n","info":{"declType":"value","type":{"annotation":[],"contents":[{"annotation":[],"contents":[{"annotation":[],"contents":[["Prim"],"Function"],"tag":"TypeConstructor"},{"annotation":[],"contents":[["Prim"],"Number"],"tag":"TypeConstructor"}],"tag":"TypeApp"},{"annotation":[],"contents":[{"annotation":[],"contents":[{"annotation":[],"contents":[["Prim"],"Function"],"tag":"TypeConstructor"},{"annotation":[],"contents":[["Prim"],"Number"],"tag":"TypeConstructor"}],"tag":"TypeApp"},{"annotation":[],"contents":[["Lattice","Services","Physics","VectorMath"],"Vec2"],"tag":"TypeConstructor"}],"tag":"TypeApp"}],"tag":"TypeApp"}},"kind":null,"sourceSpan":{"end":[63,35],"name":"src/Lattice/Services/Physics/VectorMath.purs","start":[63,1]},"title":"create"},{"children":[],"comments":"Clone a vector (identity, for API compatibility)\n","info":{"declType":"value","type":{"annotation":[],"contents":[{"annotation":[],"contents":[{"annotation":[],"contents":[["Prim"],"Function"],"tag":"TypeConstructor"},{"annotation":[],"contents":[["Lattice","Services","Physics","VectorMath"],"Vec2"],"tag":"TypeConstructor"}],"tag":"TypeApp"},{"annotation":[],"contents":[["Lattice","Services","Physics","VectorMath"],"Vec2"],"tag":"TypeConstructor"}],"tag":"TypeApp"}},"kind":null,"sourceSpan":{"end":[67,22],"name":"src/Lattice/Services/Physics/VectorMath.purs","start":[67,1]},"title":"clone"},{"children":[],"comments":"Vector addition\n","info":{"declType":"value","type":{"annotation":[],"contents":[{"annotation":[],"contents":[{"annotation":[],"contents":[["Prim"],"Function"],"tag":"TypeConstructor"},{"annotation":[],"contents":[["Lattice","Services","Physics","VectorMath"],"Vec2"],"tag":"TypeConstructor"}],"tag":"TypeApp"},{"annotation":[],"contents":[{"annotation":[],"contents":[{"annotation":[],"contents":[["Prim"],"Function"],"tag":"TypeConstructor"},{"annotation":[],"contents":[["Lattice","Services","Physics","VectorMath"],"Vec2"],"tag":"TypeConstructor"}],"tag":"TypeApp"},{"annotation":[],"contents":[["Lattice","Services","Physics","VectorMath"],"Vec2"],"tag":"TypeConstructor"}],"tag":"TypeApp"}],"tag":"TypeApp"}},"kind":null,"sourceSpan":{"end":[75,28],"name":"src/Lattice/Services/Physics/VectorMath.purs","start":[75,1]},"title":"add"},{"children":[],"comments":"Vector subtraction\n","info":{"declType":"value","type":{"annotation":[],"contents":[{"annotation":[],"contents":[{"annotation":[],"contents":[["Prim"],"Function"],"tag":"TypeConstructor"},{"annotation":[],"contents":[["Lattice","Services","Physics","VectorMath"],"Vec2"],"tag":"TypeConstructor"}],"tag":"TypeApp"},{"annotation":[],"contents":[{"annotation":[],"contents":[{"annotation":[],"contents":[["Prim"],"Function"],"tag":"TypeConstructor"},{"annotation":[],"contents":[["Lattice","Services","Physics","VectorMath"],"Vec2"],"tag":"TypeConstructor"}],"tag":"TypeApp"},{"annotation":[],"contents":[["Lattice","Services","Physics","VectorMath"],"Vec2"],"tag":"TypeConstructor"}],"tag":"TypeApp"}],"tag":"TypeApp"}},"kind":null,"sourceSpan":{"end":[79,28],"name":"src/Lattice/Services/Physics/VectorMath.purs","start":[79,1]},"title":"sub"},{"children":[],"comments":"Scalar multiplication\n","info":{"declType":"value","type":{"annotation":[],"contents":[{"annotation":[],"contents":[{"annotation":[],"contents":[["Prim"],"Function"],"tag":"TypeConstructor"},{"annotation":[],"contents":[["Lattice","Services","Physics","VectorMath"],"Vec2"],"tag":"TypeConstructor"}],"tag":"TypeApp"},{"annotation":[],"contents":[{"annotation":[],"contents":[{"annotation":[],"contents":[["Prim"],"Function"],"tag":"TypeConstructor"},{"annotation":[],"contents":[["Prim"],"Number"],"tag":"TypeConstructor"}],"tag":"TypeApp"},{"annotation":[],"contents":[["Lattice","Services","Physics","VectorMath"],"Vec2"],"tag":"TypeConstructor"}],"tag":"TypeApp"}],"tag":"TypeApp"}},"kind":null,"sourceSpan":{"end":[83,32],"name":"src/Lattice/Services/Physics/VectorMath.purs","start":[83,1]},"title":"scale"},{"children":[],"comments":"Vector negation\n","info":{"declType":"value","type":{"annotation":[],"contents":[{"annotation":[],"contents":[{"annotation":[],"contents":[["Prim"],"Function"],"tag":"TypeConstructor"},{"annotation":[],"contents":[["Lattice","Services","Physics","VectorMath"],"Vec2"],"tag":"TypeConstructor"}],"tag":"TypeApp"},{"annotation":[],"contents":[["Lattice","Services","Physics","VectorMath"],"Vec2"],"tag":"TypeConstructor"}],"tag":"TypeApp"}},"kind":null,"sourceSpan":{"end":[87,23],"name":"src/Lattice/Services/Physics/VectorMath.purs","start":[87,1]},"title":"negate"},{"children":[],"comments":"Dot product of two vectors\n","info":{"declType":"value","type":{"annotation":[],"contents":[{"annotation":[],"contents":[{"annotation":[],"contents":[["Prim"],"Function"],"tag":"TypeConstructor"},{"annotation":[],"contents":[["Lattice","Services","Physics","VectorMath"],"Vec2"],"tag":"TypeConstructor"}],"tag":"TypeApp"},{"annotation":[],"contents":[{"annotation":[],"contents":[{"annotation":[],"contents":[["Prim"],"Function"],"tag":"TypeConstructor"},{"annotation":[],"contents":[["Lattice","Services","Physics","VectorMath"],"Vec2"],"tag":"TypeConstructor"}],"tag":"TypeApp"},{"annotation":[],"contents":[["Prim"],"Number"],"tag":"TypeConstructor"}],"tag":"TypeApp"}],"tag":"TypeApp"}},"kind":null,"sourceSpan":{"end":[95,30],"name":"src/Lattice/Services/Physics/VectorMath.purs","start":[95,1]},"title":"dot"},{"children":[],"comments":"2D cross product (pseudo-cross, returns scalar).\n\nThis is the Z component of the 3D cross product with z=0.\nGeometrically: |a| * |b| * sin(angle from a to b)\n","info":{"declType":"value","type":{"annotation":[],"contents":[{"annotation":[],"contents":[{"annotation":[],"contents":[["Prim"],"Function"],"tag":"TypeConstructor"},{"annotation":[],"contents":[["Lattice","Services","Physics","VectorMath"],"Vec2"],"tag":"TypeConstructor"}],"tag":"TypeApp"},{"annotation":[],"contents":[{"annotation":[],"contents":[{"annotation":[],"contents":[["Prim"],"Function"],"tag":"TypeConstructor"},{"annotation":[],"contents":[["Lattice","Services","Physics","VectorMath"],"Vec2"],"tag":"TypeConstructor"}],"tag":"TypeApp"},{"annotation":[],"contents":[["Prim"],"Number"],"tag":"TypeConstructor"}],"tag":"TypeApp"}],"tag":"TypeApp"}},"kind":null,"sourceSpan":{"end":[102,32],"name":"src/Lattice/Services/Physics/VectorMath.purs","start":[102,1]},"title":"cross"},{"children":[],"comments":"Squared length of a vector (avoids sqrt)\n","info":{"declType":"value","type":{"annotation":[],"contents":[{"annotation":[],"contents":[{"annotation":[],"contents":[["Prim"],"Function"],"tag":"TypeConstructor"},{"annotation":[],"contents":[["Lattice","Services","Physics","VectorMath"],"Vec2"],"tag":"TypeConstructor"}],"tag":"TypeApp"},{"annotation":[],"contents":[["Prim"],"Number"],"tag":"TypeConstructor"}],"tag":"TypeApp"}},"kind":null,"sourceSpan":{"end":[110,27],"name":"src/Lattice/Services/Physics/VectorMath.purs","start":[110,1]},"title":"lengthSq"},{"children":[],"comments":"Length (magnitude) of a vector\n","info":{"declType":"value","type":{"annotation":[],"contents":[{"annotation":[],"contents":[{"annotation":[],"contents":[["Prim"],"Function"],"tag":"TypeConstructor"},{"annotation":[],"contents":[["Lattice","Services","Physics","VectorMath"],"Vec2"],"tag":"TypeConstructor"}],"tag":"TypeApp"},{"annotation":[],"contents":[["Prim"],"Number"],"tag":"TypeConstructor"}],"tag":"TypeApp"}},"kind":null,"sourceSpan":{"end":[114,28],"name":"src/Lattice/Services/Physics/VectorMath.purs","start":[114,1]},"title":"vecLength"},{"children":[],"comments":"Squared distance between two points (avoids sqrt)\n","info":{"declType":"value","type":{"annotation":[],"contents":[{"annotation":[],"contents":[{"annotation":[],"contents":[["Prim"],"Function"],"tag":"TypeConstructor"},{"annotation":[],"contents":[["Lattice","Services","Physics","VectorMath"],"Vec2"],"tag":"TypeConstructor"}],"tag":"TypeApp"},{"annotation":[],"contents":[{"annotation":[],"contents":[{"annotation":[],"contents":[["Prim"],"Function"],"tag":"TypeConstructor"},{"annotation":[],"contents":[["Lattice","Services","Physics","VectorMath"],"Vec2"],"tag":"TypeConstructor"}],"tag":"TypeApp"},{"annotation":[],"contents":[["Prim"],"Number"],"tag":"TypeConstructor"}],"tag":"TypeApp"}],"tag":"TypeApp"}},"kind":null,"sourceSpan":{"end":[118,37],"name":"src/Lattice/Services/Physics/VectorMath.purs","start":[118,1]},"title":"distanceSq"},{"children":[],"comments":"Distance between two points\n","info":{"declType":"value","type":{"annotation":[],"contents":[{"annotation":[],"contents":[{"annotation":[],"contents":[["Prim"],"Function"],"tag":"TypeConstructor"},{"annotation":[],"contents":[["Lattice","Services","Physics","VectorMath"],"Vec2"],"tag":"TypeConstructor"}],"tag":"TypeApp"},{"annotation":[],"contents":[{"annotation":[],"contents":[{"annotation":[],"contents":[["Prim"],"Function"],"tag":"TypeConstructor"},{"annotation":[],"contents":[["Lattice","Services","Physics","VectorMath"],"Vec2"],"tag":"TypeConstructor"}],"tag":"TypeApp"},{"annotation":[],"contents":[["Prim"],"Number"],"tag":"TypeConstructor"}],"tag":"TypeApp"}],"tag":"TypeApp"}},"kind":null,"sourceSpan":{"end":[122,35],"name":"src/Lattice/Services/Physics/VectorMath.purs","start":[122,1]},"title":"distance"},{"children":[],"comments":"Normalize a vector to unit length.\n\nReturns zero vector if input has zero length.\n","info":{"declType":"value","type":{"annotation":[],"contents":[{"annotation":[],"contents":[{"annotation":[],"contents":[["Prim"],"Function"],"tag":"TypeConstructor"},{"annotation":[],"contents":[["Lattice","Services","Physics","VectorMath"],"Vec2"],"tag":"TypeConstructor"}],"tag":"TypeApp"},{"annotation":[],"contents":[["Lattice","Services","Physics","VectorMath"],"Vec2"],"tag":"TypeConstructor"}],"tag":"TypeApp"}},"kind":null,"sourceSpan":{"end":[132,26],"name":"src/Lattice/Services/Physics/VectorMath.purs","start":[132,1]},"title":"normalize"},{"children":[],"comments":"Get perpendicular vector (90 degrees counter-clockwise).\n\nFor (x, y), returns (-y, x).\n","info":{"declType":"value","type":{"annotation":[],"contents":[{"annotation":[],"contents":[{"annotation":[],"contents":[["Prim"],"Function"],"tag":"TypeConstructor"},{"annotation":[],"contents":[["Lattice","Services","Physics","VectorMath"],"Vec2"],"tag":"TypeConstructor"}],"tag":"TypeApp"},{"annotation":[],"contents":[["Lattice","Services","Physics","VectorMath"],"Vec2"],"tag":"TypeConstructor"}],"tag":"TypeApp"}},"kind":null,"sourceSpan":{"end":[146,30],"name":"src/Lattice/Services/Physics/VectorMath.purs","start":[146,1]},"title":"perpendicular"},{"children":[],"comments":"Rotate vector by angle (in radians).\n\nUses rotation matrix:\n```\n[cos θ  -sin θ] [x]\n[sin θ   cos θ] [y]\n```\n","info":{"declType":"value","type":{"annotation":[],"contents":[{"annotation":[],"contents":[{"annotation":[],"contents":[["Prim"],"Function"],"tag":"TypeConstructor"},{"annotation":[],"contents":[["Lattice","Services","Physics","VectorMath"],"Vec2"],"tag":"TypeConstructor"}],"tag":"TypeApp"},{"annotation":[],"contents":[{"annotation":[],"contents":[{"annotation":[],"contents":[["Prim"],"Function"],"tag":"TypeConstructor"},{"annotation":[],"contents":[["Prim"],"Number"],"tag":"TypeConstructor"}],"tag":"TypeApp"},{"annotation":[],"contents":[["Lattice","Services","Physics","VectorMath"],"Vec2"],"tag":"TypeConstructor"}],"tag":"TypeApp"}],"tag":"TypeApp"}},"kind":null,"sourceSpan":{"end":[156,33],"name":"src/Lattice/Services/Physics/VectorMath.purs","start":[156,1]},"title":"rotate"},{"children":[],"comments":"Linear interpolation between two vectors.\n\nReturns: a + (b - a) * t\n","info":{"declType":"value","type":{"annotation":[],"contents":[{"annotation":[],"contents":[{"annotation":[],"contents":[["Prim"],"Function"],"tag":"TypeConstructor"},{"annotation":[],"contents":[["Lattice","Services","Physics","VectorMath"],"Vec2"],"tag":"TypeConstructor"}],"tag":"TypeApp"},{"annotation":[],"contents":[{"annotation":[],"contents":[{"annotation":[],"contents":[["Prim"],"Function"],"tag":"TypeConstructor"},{"annotation":[],"contents":[["Lattice","Services","Physics","VectorMath"],"Vec2"],"tag":"TypeConstructor"}],"tag":"TypeApp"},{"annotation":[],"contents":[{"annotation":[],"contents":[{"annotation":[],"contents":[["Prim"],"Function"],"tag":"TypeConstructor"},{"annotation":[],"contents":[["Prim"],"Number"],"tag":"TypeConstructor"}],"tag":"TypeApp"},{"annotation":[],"contents":[["Lattice","Services","Physics","VectorMath"],"Vec2"],"tag":"TypeConstructor"}],"tag":"TypeApp"}],"tag":"TypeApp"}],"tag":"TypeApp"}},"kind":null,"sourceSpan":{"end":[169,39],"name":"src/Lattice/Services/Physics/VectorMath.purs","start":[169,1]},"title":"lerp"},{"children":[],"comments":"Project vector a onto vector b.\n\nReturns component of a in the direction of b.\n","info":{"declType":"value","type":{"annotation":[],"contents":[{"annotation":[],"contents":[{"annotation":[],"contents":[["Prim"],"Function"],"tag":"TypeConstructor"},{"annotation":[],"contents":[["Lattice","Services","Physics","VectorMath"],"Vec2"],"tag":"TypeConstructor"}],"tag":"TypeApp"},{"annotation":[],"contents":[{"annotation":[],"contents":[{"annotation":[],"contents":[["Prim"],"Function"],"tag":"TypeConstructor"},{"annotation":[],"contents":[["Lattice","Services","Physics","VectorMath"],"Vec2"],"tag":"TypeConstructor"}],"tag":"TypeApp"},{"annotation":[],"contents":[["Lattice","Services","Physics","VectorMath"],"Vec2"],"tag":"TypeConstructor"}],"tag":"TypeApp"}],"tag":"TypeApp"}},"kind":null,"sourceSpan":{"end":[181,32],"name":"src/Lattice/Services/Physics/VectorMath.purs","start":[181,1]},"title":"project"},{"children":[],"comments":"Reflect vector v off a surface with normal n.\n","info":{"declType":"value","type":{"annotation":[],"contents":[{"annotation":[],"contents":[{"annotation":[],"contents":[["Prim"],"Function"],"tag":"TypeConstructor"},{"annotation":[],"contents":[["Lattice","Services","Physics","VectorMath"],"Vec2"],"tag":"TypeConstructor"}],"tag":"TypeApp"},{"annotation":[],"contents":[{"annotation":[],"contents":[{"annotation":[],"contents":[["Prim"],"Function"],"tag":"TypeConstructor"},{"annotation":[],"contents":[["Lattice","Services","Physics","VectorMath"],"Vec2"],"tag":"TypeConstructor"}],"tag":"TypeApp"},{"annotation":[],"contents":[["Lattice","Services","Physics","VectorMath"],"Vec2"],"tag":"TypeConstructor"}],"tag":"TypeApp"}],"tag":"TypeApp"}},"kind":null,"sourceSpan":{"end":[190,32],"name":"src/Lattice/Services/Physics/VectorMath.purs","start":[190,1]},"title":"reflect"},{"children":[],"comments":"Get angle of vector from positive x-axis (in radians).\n","info":{"declType":"value","type":{"annotation":[],"contents":[{"annotation":[],"contents":[{"annotation":[],"contents":[["Prim"],"Function"],"tag":"TypeConstructor"},{"annotation":[],"contents":[["Lattice","Services","Physics","VectorMath"],"Vec2"],"tag":"TypeConstructor"}],"tag":"TypeApp"},{"annotation":[],"contents":[["Prim"],"Number"],"tag":"TypeConstructor"}],"tag":"TypeApp"}},"kind":null,"sourceSpan":{"end":[200,24],"name":"src/Lattice/Services/Physics/VectorMath.purs","start":[200,1]},"title":"angle"},{"children":[],"comments":"Get angle between two vectors (in radians).\n\nReturns 0 if either vector has zero length.\n","info":{"declType":"value","type":{"annotation":[],"contents":[{"annotation":[],"contents":[{"annotation":[],"contents":[["Prim"],"Function"],"tag":"TypeConstructor"},{"annotation":[],"contents":[["Lattice","Services","Physics","VectorMath"],"Vec2"],"tag":"TypeConstructor"}],"tag":"TypeApp"},{"annotation":[],"contents":[{"annotation":[],"contents":[{"annotation":[],"contents":[["Prim"],"Function"],"tag":"TypeConstructor"},{"annotation":[],"contents":[["Lattice","Services","Physics","VectorMath"],"Vec2"],"tag":"TypeConstructor"}],"tag":"TypeApp"},{"annotation":[],"contents":[["Prim"],"Number"],"tag":"TypeConstructor"}],"tag":"TypeApp"}],"tag":"TypeApp"}},"kind":null,"sourceSpan":{"end":[206,39],"name":"src/Lattice/Services/Physics/VectorMath.purs","start":[206,1]},"title":"angleBetween"}],"name":"Lattice.Services.Physics.VectorMath","reExports":[]}